{
  "component-definition": {
    "uuid": "e9d68747-6575-4564-8298-c92433da5dfd",
    "metadata": {
      "title": "UIAO Unified Identity-Addressing-Overlay Architecture",
      "version": "1.0",
      "oscal-version": "1.0.4",
      "last-modified": "2026-03-31T17:21:46.775063Z",
      "published": "2026-03-31T17:21:46.775063Z",
      "props": [
        {
          "name": "fedramp-impact",
          "value": "Moderate",
          "ns": "https://fedramp.gov/ns/oscal"
        },
        {
          "name": "compliance-strategy",
          "value": "OSCAL-based Telemetry Validation",
          "ns": "https://fedramp.gov/ns/oscal"
        },
        {
          "name": "ksi-dashboard",
          "value": "Operational"
        },
        {
          "name": "framework-version",
          "value": "2026.1"
        },
        {
          "name": "markup-type",
          "value": "json",
          "ns": "https://fedramp.gov/ns/oscal"
        }
      ]
    },
    "components": [
      {
        "uuid": "b68100c3-c4e0-4f68-9c9d-882c3913237a",
        "type": "service",
        "title": "Identity Control Plane",
        "description": "The authoritative identity control plane for the Unified Modernization Program",
        "props": [
          {
            "name": "uiao-pillar",
            "value": "IDENTITY"
          },
          {
            "name": "subtitle",
            "value": "Identity Provider + ICAM + Zero Trust"
          },
          {
            "name": "component-id",
            "value": "component-identity"
          }
        ],
        "remarks": "[{\"name\": \"Identity Provider\", \"role\": \"Primary Identity Provider\", \"capabilities\": [\"Conditional Access (CA)\", \"MFA / SSPR\", \"Identity Protection\", \"Authentication Strength\"]}, {\"name\": \"ICAM Governance\", \"role\": \"Identity governance and compliance\", \"capabilities\": [\"NIST 800-63 Alignment\", \"OMB M-19-17 Compliance\", \"Credentialing\", \"Access Reviews\", \"Privileged Identity Management (PIM)\", \"Joiner/Mover/Leaver Automation\"]}, {\"name\": \"Zero Trust Policy Engine\", \"role\": \"Continuous access evaluation\", \"capabilities\": [\"Identity + Device + Location + Risk\", \"Continuous Access Evaluation (CAE)\", \"Policy decisions exported to SD-WAN + Telemetry\"]}]",
        "control-implementations": [
          {
            "uuid": "da0da7ee-d7e0-45aa-9fc3-04803b507b5e",
            "source": "https://github.com/GSA/fedramp-automation/raw/main/dist/content/rev5/baselines/json/FedRAMP_rev5_MODERATE-baseline_profile.json",
            "description": "Control implementations for Identity Control Plane",
            "implemented-requirements": [
              {
                "uuid": "5b952320-ac5e-4afe-a289-60a9eb984e98",
                "control-id": "IA-2",
                "description": "Enforces phishing-resistant MFA and deterministic Identity-to-IP binding for all US-based endpoints via Entra ID and Infoblox.",
                "props": [
                  {
                    "name": "ksi-category",
                    "value": "KSI-UNKNOWN"
                  },
                  {
                    "name": "cisa-maturity",
                    "value": "Advanced"
                  },
                  {
                    "name": "evidence-source",
                    "value": "N/A"
                  }
                ],
                "remarks": "Implemented by Identity Control Plane"
              },
              {
                "uuid": "3fd440bf-92c5-4b7d-9aa1-b5969ee0361f",
                "control-id": "IA-5",
                "description": "Enforces phishing-resistant MFA and deterministic Identity-to-IP binding for all US-based endpoints via Entra ID and Infoblox.",
                "props": [
                  {
                    "name": "ksi-category",
                    "value": "KSI-UNKNOWN"
                  },
                  {
                    "name": "cisa-maturity",
                    "value": "Advanced"
                  },
                  {
                    "name": "evidence-source",
                    "value": "N/A"
                  }
                ],
                "remarks": "Implemented by Identity Control Plane"
              },
              {
                "uuid": "deb3ac19-7a9b-4006-9736-10f577e4f405",
                "control-id": "AC-19",
                "description": "Enforces phishing-resistant MFA and deterministic Identity-to-IP binding for all US-based endpoints via Entra ID and Infoblox.",
                "props": [
                  {
                    "name": "ksi-category",
                    "value": "KSI-UNKNOWN"
                  },
                  {
                    "name": "cisa-maturity",
                    "value": "Advanced"
                  },
                  {
                    "name": "evidence-source",
                    "value": "N/A"
                  }
                ],
                "remarks": "Implemented by Identity Control Plane"
              }
            ]
          },
          {
            "uuid": "257af64b-e864-445a-88bf-96a7f08d6cf8",
            "source": "https://github.com/GSA/fedramp-automation/raw/main/dist/content/rev5/baselines/json/FedRAMP_rev5_MODERATE-baseline_profile.json",
            "description": "Control implementations for Identity Control Plane",
            "implemented-requirements": [
              {
                "uuid": "3a741ca3-2895-4294-924f-5340a0fad53f",
                "control-id": "SC-7",
                "description": "Establishes a cryptographically secured overlay fabric with US-only geography enforcement.",
                "props": [
                  {
                    "name": "ksi-category",
                    "value": "KSI-UNKNOWN"
                  },
                  {
                    "name": "cisa-maturity",
                    "value": "Optimal"
                  },
                  {
                    "name": "evidence-source",
                    "value": "N/A"
                  }
                ],
                "remarks": "Implemented by Identity Control Plane"
              },
              {
                "uuid": "cbbabd04-17f7-4ff8-ac65-f63f81a293ab",
                "control-id": "SC-8",
                "description": "Establishes a cryptographically secured overlay fabric with US-only geography enforcement.",
                "props": [
                  {
                    "name": "ksi-category",
                    "value": "KSI-UNKNOWN"
                  },
                  {
                    "name": "cisa-maturity",
                    "value": "Optimal"
                  },
                  {
                    "name": "evidence-source",
                    "value": "N/A"
                  }
                ],
                "remarks": "Implemented by Identity Control Plane"
              },
              {
                "uuid": "051dfcac-be76-4119-8265-c9decf7d8db1",
                "control-id": "AC-4",
                "description": "Establishes a cryptographically secured overlay fabric with US-only geography enforcement.",
                "props": [
                  {
                    "name": "ksi-category",
                    "value": "KSI-UNKNOWN"
                  },
                  {
                    "name": "cisa-maturity",
                    "value": "Optimal"
                  },
                  {
                    "name": "evidence-source",
                    "value": "N/A"
                  }
                ],
                "remarks": "Implemented by Identity Control Plane"
              }
            ]
          },
          {
            "uuid": "d097db21-01c2-4491-8f03-d753978b7622",
            "source": "https://github.com/GSA/fedramp-automation/raw/main/dist/content/rev5/baselines/json/FedRAMP_rev5_MODERATE-baseline_profile.json",
            "description": "Control implementations for Identity Control Plane",
            "implemented-requirements": [
              {
                "uuid": "ac208ec9-4b1b-4008-a484-7c018eb9b2de",
                "control-id": "CA-7",
                "description": "Real-time drift detection and automated remediation loop via ServiceNow and GitHub SCuBA.",
                "props": [
                  {
                    "name": "ksi-category",
                    "value": "KSI-UNKNOWN"
                  },
                  {
                    "name": "cisa-maturity",
                    "value": "Optimal"
                  },
                  {
                    "name": "evidence-source",
                    "value": "N/A"
                  }
                ],
                "remarks": "Implemented by Identity Control Plane"
              },
              {
                "uuid": "a08f404d-8a1d-4a35-890a-ee72cdbd779c",
                "control-id": "CM-6",
                "description": "Real-time drift detection and automated remediation loop via ServiceNow and GitHub SCuBA.",
                "props": [
                  {
                    "name": "ksi-category",
                    "value": "KSI-UNKNOWN"
                  },
                  {
                    "name": "cisa-maturity",
                    "value": "Optimal"
                  },
                  {
                    "name": "evidence-source",
                    "value": "N/A"
                  }
                ],
                "remarks": "Implemented by Identity Control Plane"
              },
              {
                "uuid": "40d6d535-c1f0-4cae-a49f-0f3ffbfac8b0",
                "control-id": "IR-4",
                "description": "Real-time drift detection and automated remediation loop via ServiceNow and GitHub SCuBA.",
                "props": [
                  {
                    "name": "ksi-category",
                    "value": "KSI-UNKNOWN"
                  },
                  {
                    "name": "cisa-maturity",
                    "value": "Optimal"
                  },
                  {
                    "name": "evidence-source",
                    "value": "N/A"
                  }
                ],
                "remarks": "Implemented by Identity Control Plane"
              }
            ]
          },
          {
            "uuid": "cc1b7df4-43e9-450e-82e9-0d6832bd58c1",
            "source": "https://github.com/GSA/fedramp-automation/raw/main/dist/content/rev5/baselines/json/FedRAMP_rev5_MODERATE-baseline_profile.json",
            "description": "Control implementations for Identity Control Plane",
            "implemented-requirements": [
              {
                "uuid": "3cdb72e2-4e58-48dc-9811-6472e0a9bdb5",
                "control-id": "AC-4",
                "description": "Collapses legacy TIC 2.2 silos into a software-defined, identity-centric perimeter.",
                "props": [
                  {
                    "name": "ksi-category",
                    "value": "KSI-UNKNOWN"
                  },
                  {
                    "name": "cisa-maturity",
                    "value": "Advanced"
                  },
                  {
                    "name": "evidence-source",
                    "value": "N/A"
                  }
                ],
                "remarks": "Implemented by Identity Control Plane"
              },
              {
                "uuid": "aaaeb1a2-80ca-4797-8490-ed7f4dfcb066",
                "control-id": "SC-38",
                "description": "Collapses legacy TIC 2.2 silos into a software-defined, identity-centric perimeter.",
                "props": [
                  {
                    "name": "ksi-category",
                    "value": "KSI-UNKNOWN"
                  },
                  {
                    "name": "cisa-maturity",
                    "value": "Advanced"
                  },
                  {
                    "name": "evidence-source",
                    "value": "N/A"
                  }
                ],
                "remarks": "Implemented by Identity Control Plane"
              }
            ]
          },
          {
            "uuid": "f94f41cd-5790-4f23-91d6-b593a3b32976",
            "source": "https://github.com/GSA/fedramp-automation/raw/main/dist/content/rev5/baselines/json/FedRAMP_rev5_MODERATE-baseline_profile.json",
            "description": "Control implementations for Identity Control Plane",
            "implemented-requirements": [
              {
                "uuid": "b3022901-4796-4258-aaee-52de619a2e7a",
                "control-id": "SC-8",
                "description": "Anchors device and user trust to the GSA Federal Root CA with end-to-end channel binding.",
                "props": [
                  {
                    "name": "ksi-category",
                    "value": "KSI-UNKNOWN"
                  },
                  {
                    "name": "cisa-maturity",
                    "value": "Optimal"
                  },
                  {
                    "name": "evidence-source",
                    "value": "N/A"
                  }
                ],
                "remarks": "Implemented by Identity Control Plane"
              },
              {
                "uuid": "47564842-62ef-459c-8533-4941cb605109",
                "control-id": "IA-3",
                "description": "Anchors device and user trust to the GSA Federal Root CA with end-to-end channel binding.",
                "props": [
                  {
                    "name": "ksi-category",
                    "value": "KSI-UNKNOWN"
                  },
                  {
                    "name": "cisa-maturity",
                    "value": "Optimal"
                  },
                  {
                    "name": "evidence-source",
                    "value": "N/A"
                  }
                ],
                "remarks": "Implemented by Identity Control Plane"
              }
            ]
          }
        ]
      },
      {
        "uuid": "cc88567d-4aad-42f4-9a0d-1b5af22a3b73",
        "type": "service",
        "title": "Addressing Control Plane",
        "description": "The authoritative source of truth for identity-anchored addressing, DNS, DHCP, and cross-cloud reconciliation",
        "props": [
          {
            "name": "uiao-pillar",
            "value": "ADDRESSING"
          },
          {
            "name": "subtitle",
            "value": "IPAM Platform"
          },
          {
            "name": "component-id",
            "value": "component-addressing"
          }
        ],
        "remarks": "[{\"name\": \"IPAM Platform\", \"role\": \"Authoritative Source of Truth\", \"capabilities\": [\"IP address allocation and tracking\", \"Subnet creation and lifecycle management\", \"DNS zone management and record authority\", \"DHCP scope governance and lease evidence\"]}, {\"name\": \"DNS Management\", \"role\": \"Authoritative DNS zones\", \"capabilities\": [\"Internal zones managed by IPAM platform\", \"Split-horizon DNS\", \"DNS evidence tied to identity/subnet/location\"]}, {\"name\": \"DHCP Management\", \"role\": \"Scope governance\", \"capabilities\": [\"Scopes defined and owned by IPAM\", \"Lease durations aligned with device identity\", \"Automatic DNS record creation from DHCP leases\"]}, {\"name\": \"Cloud IPAM Reconciliation\", \"role\": \"Multi-cloud addressing truth\", \"capabilities\": []}]",
        "control-implementations": [
          {
            "uuid": "278b2118-0643-4195-8902-f4e53da2e3c0",
            "source": "https://github.com/GSA/fedramp-automation/raw/main/dist/content/rev5/baselines/json/FedRAMP_rev5_MODERATE-baseline_profile.json",
            "description": "Control implementations for Addressing Control Plane",
            "implemented-requirements": [
              {
                "uuid": "1ef44b1d-f6f6-4130-8e22-09f7c8d09cd4",
                "control-id": "IA-2",
                "description": "Enforces phishing-resistant MFA and deterministic Identity-to-IP binding for all US-based endpoints via Entra ID and Infoblox.",
                "props": [
                  {
                    "name": "ksi-category",
                    "value": "KSI-UNKNOWN"
                  },
                  {
                    "name": "cisa-maturity",
                    "value": "Advanced"
                  },
                  {
                    "name": "evidence-source",
                    "value": "N/A"
                  }
                ],
                "remarks": "Implemented by Addressing Control Plane"
              },
              {
                "uuid": "ed855da9-36f0-4ceb-ad0b-ae3774cf283a",
                "control-id": "IA-5",
                "description": "Enforces phishing-resistant MFA and deterministic Identity-to-IP binding for all US-based endpoints via Entra ID and Infoblox.",
                "props": [
                  {
                    "name": "ksi-category",
                    "value": "KSI-UNKNOWN"
                  },
                  {
                    "name": "cisa-maturity",
                    "value": "Advanced"
                  },
                  {
                    "name": "evidence-source",
                    "value": "N/A"
                  }
                ],
                "remarks": "Implemented by Addressing Control Plane"
              },
              {
                "uuid": "88fd7c08-3c20-4f0b-a6c4-6d4762904c7a",
                "control-id": "AC-19",
                "description": "Enforces phishing-resistant MFA and deterministic Identity-to-IP binding for all US-based endpoints via Entra ID and Infoblox.",
                "props": [
                  {
                    "name": "ksi-category",
                    "value": "KSI-UNKNOWN"
                  },
                  {
                    "name": "cisa-maturity",
                    "value": "Advanced"
                  },
                  {
                    "name": "evidence-source",
                    "value": "N/A"
                  }
                ],
                "remarks": "Implemented by Addressing Control Plane"
              }
            ]
          },
          {
            "uuid": "ab1354d6-4262-469a-ad54-3647dd68b4cd",
            "source": "https://github.com/GSA/fedramp-automation/raw/main/dist/content/rev5/baselines/json/FedRAMP_rev5_MODERATE-baseline_profile.json",
            "description": "Control implementations for Addressing Control Plane",
            "implemented-requirements": [
              {
                "uuid": "1e9cc02d-820e-418b-bb17-2f108057d421",
                "control-id": "SC-7",
                "description": "Establishes a cryptographically secured overlay fabric with US-only geography enforcement.",
                "props": [
                  {
                    "name": "ksi-category",
                    "value": "KSI-UNKNOWN"
                  },
                  {
                    "name": "cisa-maturity",
                    "value": "Optimal"
                  },
                  {
                    "name": "evidence-source",
                    "value": "N/A"
                  }
                ],
                "remarks": "Implemented by Addressing Control Plane"
              },
              {
                "uuid": "f216f78f-cb7f-465f-979f-3304f65c2458",
                "control-id": "SC-8",
                "description": "Establishes a cryptographically secured overlay fabric with US-only geography enforcement.",
                "props": [
                  {
                    "name": "ksi-category",
                    "value": "KSI-UNKNOWN"
                  },
                  {
                    "name": "cisa-maturity",
                    "value": "Optimal"
                  },
                  {
                    "name": "evidence-source",
                    "value": "N/A"
                  }
                ],
                "remarks": "Implemented by Addressing Control Plane"
              },
              {
                "uuid": "5a8bc033-398f-493e-a040-2926d0c7db23",
                "control-id": "AC-4",
                "description": "Establishes a cryptographically secured overlay fabric with US-only geography enforcement.",
                "props": [
                  {
                    "name": "ksi-category",
                    "value": "KSI-UNKNOWN"
                  },
                  {
                    "name": "cisa-maturity",
                    "value": "Optimal"
                  },
                  {
                    "name": "evidence-source",
                    "value": "N/A"
                  }
                ],
                "remarks": "Implemented by Addressing Control Plane"
              }
            ]
          },
          {
            "uuid": "e2cfdc38-aee3-4a41-9787-f4585497c6f0",
            "source": "https://github.com/GSA/fedramp-automation/raw/main/dist/content/rev5/baselines/json/FedRAMP_rev5_MODERATE-baseline_profile.json",
            "description": "Control implementations for Addressing Control Plane",
            "implemented-requirements": [
              {
                "uuid": "ab233dd9-c666-4abd-948f-b031063af017",
                "control-id": "CA-7",
                "description": "Real-time drift detection and automated remediation loop via ServiceNow and GitHub SCuBA.",
                "props": [
                  {
                    "name": "ksi-category",
                    "value": "KSI-UNKNOWN"
                  },
                  {
                    "name": "cisa-maturity",
                    "value": "Optimal"
                  },
                  {
                    "name": "evidence-source",
                    "value": "N/A"
                  }
                ],
                "remarks": "Implemented by Addressing Control Plane"
              },
              {
                "uuid": "6b8fb1a9-3129-4807-a72e-bf390cc914fa",
                "control-id": "CM-6",
                "description": "Real-time drift detection and automated remediation loop via ServiceNow and GitHub SCuBA.",
                "props": [
                  {
                    "name": "ksi-category",
                    "value": "KSI-UNKNOWN"
                  },
                  {
                    "name": "cisa-maturity",
                    "value": "Optimal"
                  },
                  {
                    "name": "evidence-source",
                    "value": "N/A"
                  }
                ],
                "remarks": "Implemented by Addressing Control Plane"
              },
              {
                "uuid": "a116d281-1322-4ccb-9713-a35ce361c2a7",
                "control-id": "IR-4",
                "description": "Real-time drift detection and automated remediation loop via ServiceNow and GitHub SCuBA.",
                "props": [
                  {
                    "name": "ksi-category",
                    "value": "KSI-UNKNOWN"
                  },
                  {
                    "name": "cisa-maturity",
                    "value": "Optimal"
                  },
                  {
                    "name": "evidence-source",
                    "value": "N/A"
                  }
                ],
                "remarks": "Implemented by Addressing Control Plane"
              }
            ]
          },
          {
            "uuid": "662188fe-15c6-43ed-9ee0-79e661e9e74a",
            "source": "https://github.com/GSA/fedramp-automation/raw/main/dist/content/rev5/baselines/json/FedRAMP_rev5_MODERATE-baseline_profile.json",
            "description": "Control implementations for Addressing Control Plane",
            "implemented-requirements": [
              {
                "uuid": "5e901dff-ba00-4270-b173-02922e106a54",
                "control-id": "AC-4",
                "description": "Collapses legacy TIC 2.2 silos into a software-defined, identity-centric perimeter.",
                "props": [
                  {
                    "name": "ksi-category",
                    "value": "KSI-UNKNOWN"
                  },
                  {
                    "name": "cisa-maturity",
                    "value": "Advanced"
                  },
                  {
                    "name": "evidence-source",
                    "value": "N/A"
                  }
                ],
                "remarks": "Implemented by Addressing Control Plane"
              },
              {
                "uuid": "d59940cb-8d24-41ea-948d-ea3a60abed0c",
                "control-id": "SC-38",
                "description": "Collapses legacy TIC 2.2 silos into a software-defined, identity-centric perimeter.",
                "props": [
                  {
                    "name": "ksi-category",
                    "value": "KSI-UNKNOWN"
                  },
                  {
                    "name": "cisa-maturity",
                    "value": "Advanced"
                  },
                  {
                    "name": "evidence-source",
                    "value": "N/A"
                  }
                ],
                "remarks": "Implemented by Addressing Control Plane"
              }
            ]
          },
          {
            "uuid": "caf7c661-03b7-479b-93ce-a16dcdc00a1a",
            "source": "https://github.com/GSA/fedramp-automation/raw/main/dist/content/rev5/baselines/json/FedRAMP_rev5_MODERATE-baseline_profile.json",
            "description": "Control implementations for Addressing Control Plane",
            "implemented-requirements": [
              {
                "uuid": "71580e92-dad8-4085-b1dd-4efc3febc4fa",
                "control-id": "SC-8",
                "description": "Anchors device and user trust to the GSA Federal Root CA with end-to-end channel binding.",
                "props": [
                  {
                    "name": "ksi-category",
                    "value": "KSI-UNKNOWN"
                  },
                  {
                    "name": "cisa-maturity",
                    "value": "Optimal"
                  },
                  {
                    "name": "evidence-source",
                    "value": "N/A"
                  }
                ],
                "remarks": "Implemented by Addressing Control Plane"
              },
              {
                "uuid": "697f927e-34a4-4712-9845-4b6da50f2528",
                "control-id": "IA-3",
                "description": "Anchors device and user trust to the GSA Federal Root CA with end-to-end channel binding.",
                "props": [
                  {
                    "name": "ksi-category",
                    "value": "KSI-UNKNOWN"
                  },
                  {
                    "name": "cisa-maturity",
                    "value": "Optimal"
                  },
                  {
                    "name": "evidence-source",
                    "value": "N/A"
                  }
                ],
                "remarks": "Implemented by Addressing Control Plane"
              }
            ]
          }
        ]
      },
      {
        "uuid": "e37ac00f-f03c-4152-9e30-c0e4bd5345d5",
        "type": "service",
        "title": "Network Control Plane",
        "description": "A governed, identity-anchored, telemetry-driven routing and segmentation system",
        "props": [
          {
            "name": "uiao-pillar",
            "value": "NETWORK"
          },
          {
            "name": "subtitle",
            "value": "SD-WAN Platform"
          },
          {
            "name": "component-id",
            "value": "component-network"
          }
        ],
        "remarks": "[{\"name\": \"SD-WAN Policy Engine\", \"role\": \"Centralized policy engine\", \"capabilities\": [\"Pushes routing/segmentation/security policies to WAN edges\", \"Integrates with identity and telemetry for INR\"]}, {\"name\": \"SD-WAN Control Orchestrator\", \"role\": \"Control-plane orchestrator\", \"capabilities\": [\"OMP route distribution\", \"Security and segmentation policy distribution\"]}, {\"name\": \"SD-WAN Orchestration Controller\", \"role\": \"Secure orchestration\", \"capabilities\": [\"Secure control-plane connections\", \"WAN edge device authentication\"]}, {\"name\": \"WAN Edge Devices\", \"role\": \"Enforcement points\", \"capabilities\": [\"Segmentation and routing enforcement\", \"IPSEC/GRE overlay maintenance\", \"Telemetry emission\"]}]",
        "control-implementations": [
          {
            "uuid": "b7ccef72-fa2b-4570-b687-94828cc5c190",
            "source": "https://github.com/GSA/fedramp-automation/raw/main/dist/content/rev5/baselines/json/FedRAMP_rev5_MODERATE-baseline_profile.json",
            "description": "Control implementations for Network Control Plane",
            "implemented-requirements": [
              {
                "uuid": "67944144-33df-4a16-aa3e-962cf09bc423",
                "control-id": "IA-2",
                "description": "Enforces phishing-resistant MFA and deterministic Identity-to-IP binding for all US-based endpoints via Entra ID and Infoblox.",
                "props": [
                  {
                    "name": "ksi-category",
                    "value": "KSI-UNKNOWN"
                  },
                  {
                    "name": "cisa-maturity",
                    "value": "Advanced"
                  },
                  {
                    "name": "evidence-source",
                    "value": "N/A"
                  }
                ],
                "remarks": "Implemented by Network Control Plane"
              },
              {
                "uuid": "68d96425-194f-4e70-a50a-535387f8b0a3",
                "control-id": "IA-5",
                "description": "Enforces phishing-resistant MFA and deterministic Identity-to-IP binding for all US-based endpoints via Entra ID and Infoblox.",
                "props": [
                  {
                    "name": "ksi-category",
                    "value": "KSI-UNKNOWN"
                  },
                  {
                    "name": "cisa-maturity",
                    "value": "Advanced"
                  },
                  {
                    "name": "evidence-source",
                    "value": "N/A"
                  }
                ],
                "remarks": "Implemented by Network Control Plane"
              },
              {
                "uuid": "f590f1b2-8fb2-4dea-ae83-b1e385303c93",
                "control-id": "AC-19",
                "description": "Enforces phishing-resistant MFA and deterministic Identity-to-IP binding for all US-based endpoints via Entra ID and Infoblox.",
                "props": [
                  {
                    "name": "ksi-category",
                    "value": "KSI-UNKNOWN"
                  },
                  {
                    "name": "cisa-maturity",
                    "value": "Advanced"
                  },
                  {
                    "name": "evidence-source",
                    "value": "N/A"
                  }
                ],
                "remarks": "Implemented by Network Control Plane"
              }
            ]
          },
          {
            "uuid": "0ff7fd1d-8eee-48a5-a202-3bb741508acc",
            "source": "https://github.com/GSA/fedramp-automation/raw/main/dist/content/rev5/baselines/json/FedRAMP_rev5_MODERATE-baseline_profile.json",
            "description": "Control implementations for Network Control Plane",
            "implemented-requirements": [
              {
                "uuid": "3799f012-5bf6-4ab2-80e5-2c15bd5cf6fd",
                "control-id": "SC-7",
                "description": "Establishes a cryptographically secured overlay fabric with US-only geography enforcement.",
                "props": [
                  {
                    "name": "ksi-category",
                    "value": "KSI-UNKNOWN"
                  },
                  {
                    "name": "cisa-maturity",
                    "value": "Optimal"
                  },
                  {
                    "name": "evidence-source",
                    "value": "N/A"
                  }
                ],
                "remarks": "Implemented by Network Control Plane"
              },
              {
                "uuid": "da3e467c-f8f6-4f46-98c7-da38974ee938",
                "control-id": "SC-8",
                "description": "Establishes a cryptographically secured overlay fabric with US-only geography enforcement.",
                "props": [
                  {
                    "name": "ksi-category",
                    "value": "KSI-UNKNOWN"
                  },
                  {
                    "name": "cisa-maturity",
                    "value": "Optimal"
                  },
                  {
                    "name": "evidence-source",
                    "value": "N/A"
                  }
                ],
                "remarks": "Implemented by Network Control Plane"
              },
              {
                "uuid": "aa55f419-c0a9-41b7-bf8e-4987c15ae317",
                "control-id": "AC-4",
                "description": "Establishes a cryptographically secured overlay fabric with US-only geography enforcement.",
                "props": [
                  {
                    "name": "ksi-category",
                    "value": "KSI-UNKNOWN"
                  },
                  {
                    "name": "cisa-maturity",
                    "value": "Optimal"
                  },
                  {
                    "name": "evidence-source",
                    "value": "N/A"
                  }
                ],
                "remarks": "Implemented by Network Control Plane"
              }
            ]
          },
          {
            "uuid": "1b2d6b19-17bf-4c11-8471-c65b749ce4a1",
            "source": "https://github.com/GSA/fedramp-automation/raw/main/dist/content/rev5/baselines/json/FedRAMP_rev5_MODERATE-baseline_profile.json",
            "description": "Control implementations for Network Control Plane",
            "implemented-requirements": [
              {
                "uuid": "698ada6d-49ba-423b-86b2-90ed5b775e71",
                "control-id": "CA-7",
                "description": "Real-time drift detection and automated remediation loop via ServiceNow and GitHub SCuBA.",
                "props": [
                  {
                    "name": "ksi-category",
                    "value": "KSI-UNKNOWN"
                  },
                  {
                    "name": "cisa-maturity",
                    "value": "Optimal"
                  },
                  {
                    "name": "evidence-source",
                    "value": "N/A"
                  }
                ],
                "remarks": "Implemented by Network Control Plane"
              },
              {
                "uuid": "242cf498-e89c-4d20-aaa9-bd31f147ec06",
                "control-id": "CM-6",
                "description": "Real-time drift detection and automated remediation loop via ServiceNow and GitHub SCuBA.",
                "props": [
                  {
                    "name": "ksi-category",
                    "value": "KSI-UNKNOWN"
                  },
                  {
                    "name": "cisa-maturity",
                    "value": "Optimal"
                  },
                  {
                    "name": "evidence-source",
                    "value": "N/A"
                  }
                ],
                "remarks": "Implemented by Network Control Plane"
              },
              {
                "uuid": "e4784fce-0b63-4d24-a377-58d8a21149e5",
                "control-id": "IR-4",
                "description": "Real-time drift detection and automated remediation loop via ServiceNow and GitHub SCuBA.",
                "props": [
                  {
                    "name": "ksi-category",
                    "value": "KSI-UNKNOWN"
                  },
                  {
                    "name": "cisa-maturity",
                    "value": "Optimal"
                  },
                  {
                    "name": "evidence-source",
                    "value": "N/A"
                  }
                ],
                "remarks": "Implemented by Network Control Plane"
              }
            ]
          },
          {
            "uuid": "973cfa44-7860-4841-8fe6-426963866c06",
            "source": "https://github.com/GSA/fedramp-automation/raw/main/dist/content/rev5/baselines/json/FedRAMP_rev5_MODERATE-baseline_profile.json",
            "description": "Control implementations for Network Control Plane",
            "implemented-requirements": [
              {
                "uuid": "2b6ada16-0380-4d0c-9bb4-dd47cf0d439b",
                "control-id": "AC-4",
                "description": "Collapses legacy TIC 2.2 silos into a software-defined, identity-centric perimeter.",
                "props": [
                  {
                    "name": "ksi-category",
                    "value": "KSI-UNKNOWN"
                  },
                  {
                    "name": "cisa-maturity",
                    "value": "Advanced"
                  },
                  {
                    "name": "evidence-source",
                    "value": "N/A"
                  }
                ],
                "remarks": "Implemented by Network Control Plane"
              },
              {
                "uuid": "067ee6a6-670c-4dd2-9ff2-b79e7c7c862b",
                "control-id": "SC-38",
                "description": "Collapses legacy TIC 2.2 silos into a software-defined, identity-centric perimeter.",
                "props": [
                  {
                    "name": "ksi-category",
                    "value": "KSI-UNKNOWN"
                  },
                  {
                    "name": "cisa-maturity",
                    "value": "Advanced"
                  },
                  {
                    "name": "evidence-source",
                    "value": "N/A"
                  }
                ],
                "remarks": "Implemented by Network Control Plane"
              }
            ]
          },
          {
            "uuid": "578a51ca-6fb1-4ec4-a885-e8bb5faae124",
            "source": "https://github.com/GSA/fedramp-automation/raw/main/dist/content/rev5/baselines/json/FedRAMP_rev5_MODERATE-baseline_profile.json",
            "description": "Control implementations for Network Control Plane",
            "implemented-requirements": [
              {
                "uuid": "e75e54d0-6ee4-4bc2-8c3f-3f909695e8b5",
                "control-id": "SC-8",
                "description": "Anchors device and user trust to the GSA Federal Root CA with end-to-end channel binding.",
                "props": [
                  {
                    "name": "ksi-category",
                    "value": "KSI-UNKNOWN"
                  },
                  {
                    "name": "cisa-maturity",
                    "value": "Optimal"
                  },
                  {
                    "name": "evidence-source",
                    "value": "N/A"
                  }
                ],
                "remarks": "Implemented by Network Control Plane"
              },
              {
                "uuid": "00ac89a2-a366-4839-aea3-4e31f108b880",
                "control-id": "IA-3",
                "description": "Anchors device and user trust to the GSA Federal Root CA with end-to-end channel binding.",
                "props": [
                  {
                    "name": "ksi-category",
                    "value": "KSI-UNKNOWN"
                  },
                  {
                    "name": "cisa-maturity",
                    "value": "Optimal"
                  },
                  {
                    "name": "evidence-source",
                    "value": "N/A"
                  }
                ],
                "remarks": "Implemented by Network Control Plane"
              }
            ]
          }
        ]
      },
      {
        "uuid": "841ed7fb-9149-4aa8-aa14-0beaa19f7a11",
        "type": "service",
        "title": "Telemetry Control Plane",
        "description": "The substrate of truth for detection, diagnosis, governance, and automation",
        "props": [
          {
            "name": "uiao-pillar",
            "value": "TELEMETRY"
          },
          {
            "name": "subtitle",
            "value": "Detection, diagnosis, governance, and automation"
          },
          {
            "name": "component-id",
            "value": "component-telemetry"
          }
        ],
        "remarks": "[{\"name\": \"SIEM Platform\", \"role\": \"Aggregation, correlation, compliance\", \"capabilities\": []}, {\"name\": \"Cloud Monitoring Platform\", \"role\": \"Cloud-native telemetry\", \"capabilities\": []}, {\"name\": \"Network Performance Monitor\", \"role\": \"Network path truth\", \"capabilities\": []}, {\"name\": \"IPAM Platform\", \"role\": \"DNS/DHCP/IPAM evidence\", \"capabilities\": []}, {\"name\": \"Endpoint Detection Platform\", \"role\": \"Endpoint truth\", \"capabilities\": []}]",
        "control-implementations": [
          {
            "uuid": "5c16343c-280d-4be5-b1e6-a1ea674545f1",
            "source": "https://github.com/GSA/fedramp-automation/raw/main/dist/content/rev5/baselines/json/FedRAMP_rev5_MODERATE-baseline_profile.json",
            "description": "Control implementations for Telemetry Control Plane",
            "implemented-requirements": [
              {
                "uuid": "a084eaa3-f1c9-46da-9e2a-2454277d3e93",
                "control-id": "IA-2",
                "description": "Enforces phishing-resistant MFA and deterministic Identity-to-IP binding for all US-based endpoints via Entra ID and Infoblox.",
                "props": [
                  {
                    "name": "ksi-category",
                    "value": "KSI-UNKNOWN"
                  },
                  {
                    "name": "cisa-maturity",
                    "value": "Advanced"
                  },
                  {
                    "name": "evidence-source",
                    "value": "N/A"
                  }
                ],
                "remarks": "Implemented by Telemetry Control Plane"
              },
              {
                "uuid": "1e8a0e61-d0e4-4b83-885a-593165e279bf",
                "control-id": "IA-5",
                "description": "Enforces phishing-resistant MFA and deterministic Identity-to-IP binding for all US-based endpoints via Entra ID and Infoblox.",
                "props": [
                  {
                    "name": "ksi-category",
                    "value": "KSI-UNKNOWN"
                  },
                  {
                    "name": "cisa-maturity",
                    "value": "Advanced"
                  },
                  {
                    "name": "evidence-source",
                    "value": "N/A"
                  }
                ],
                "remarks": "Implemented by Telemetry Control Plane"
              },
              {
                "uuid": "fbd9697c-2d21-42cb-9e46-5e45f1fe6c58",
                "control-id": "AC-19",
                "description": "Enforces phishing-resistant MFA and deterministic Identity-to-IP binding for all US-based endpoints via Entra ID and Infoblox.",
                "props": [
                  {
                    "name": "ksi-category",
                    "value": "KSI-UNKNOWN"
                  },
                  {
                    "name": "cisa-maturity",
                    "value": "Advanced"
                  },
                  {
                    "name": "evidence-source",
                    "value": "N/A"
                  }
                ],
                "remarks": "Implemented by Telemetry Control Plane"
              }
            ]
          },
          {
            "uuid": "c71f4431-8a6a-40a9-9c8a-7bfb61090133",
            "source": "https://github.com/GSA/fedramp-automation/raw/main/dist/content/rev5/baselines/json/FedRAMP_rev5_MODERATE-baseline_profile.json",
            "description": "Control implementations for Telemetry Control Plane",
            "implemented-requirements": [
              {
                "uuid": "df7a5f9a-6a15-4d07-bea6-3bd73cd4bcc1",
                "control-id": "SC-7",
                "description": "Establishes a cryptographically secured overlay fabric with US-only geography enforcement.",
                "props": [
                  {
                    "name": "ksi-category",
                    "value": "KSI-UNKNOWN"
                  },
                  {
                    "name": "cisa-maturity",
                    "value": "Optimal"
                  },
                  {
                    "name": "evidence-source",
                    "value": "N/A"
                  }
                ],
                "remarks": "Implemented by Telemetry Control Plane"
              },
              {
                "uuid": "d0a4d1f1-751e-4c77-a0c6-bb81c93edf1a",
                "control-id": "SC-8",
                "description": "Establishes a cryptographically secured overlay fabric with US-only geography enforcement.",
                "props": [
                  {
                    "name": "ksi-category",
                    "value": "KSI-UNKNOWN"
                  },
                  {
                    "name": "cisa-maturity",
                    "value": "Optimal"
                  },
                  {
                    "name": "evidence-source",
                    "value": "N/A"
                  }
                ],
                "remarks": "Implemented by Telemetry Control Plane"
              },
              {
                "uuid": "b257cf6c-d1fd-4295-a339-ececcf1588e1",
                "control-id": "AC-4",
                "description": "Establishes a cryptographically secured overlay fabric with US-only geography enforcement.",
                "props": [
                  {
                    "name": "ksi-category",
                    "value": "KSI-UNKNOWN"
                  },
                  {
                    "name": "cisa-maturity",
                    "value": "Optimal"
                  },
                  {
                    "name": "evidence-source",
                    "value": "N/A"
                  }
                ],
                "remarks": "Implemented by Telemetry Control Plane"
              }
            ]
          },
          {
            "uuid": "e81c6c45-6e7f-4bab-84d6-8f17b3b3a7ba",
            "source": "https://github.com/GSA/fedramp-automation/raw/main/dist/content/rev5/baselines/json/FedRAMP_rev5_MODERATE-baseline_profile.json",
            "description": "Control implementations for Telemetry Control Plane",
            "implemented-requirements": [
              {
                "uuid": "b9710fa2-2c25-40e3-b74d-4c180eca59e9",
                "control-id": "CA-7",
                "description": "Real-time drift detection and automated remediation loop via ServiceNow and GitHub SCuBA.",
                "props": [
                  {
                    "name": "ksi-category",
                    "value": "KSI-UNKNOWN"
                  },
                  {
                    "name": "cisa-maturity",
                    "value": "Optimal"
                  },
                  {
                    "name": "evidence-source",
                    "value": "N/A"
                  }
                ],
                "remarks": "Implemented by Telemetry Control Plane"
              },
              {
                "uuid": "df242af5-f825-4a78-a7aa-4989397fe542",
                "control-id": "CM-6",
                "description": "Real-time drift detection and automated remediation loop via ServiceNow and GitHub SCuBA.",
                "props": [
                  {
                    "name": "ksi-category",
                    "value": "KSI-UNKNOWN"
                  },
                  {
                    "name": "cisa-maturity",
                    "value": "Optimal"
                  },
                  {
                    "name": "evidence-source",
                    "value": "N/A"
                  }
                ],
                "remarks": "Implemented by Telemetry Control Plane"
              },
              {
                "uuid": "bb51b314-ac60-4dba-b8b2-4bee2be8a92d",
                "control-id": "IR-4",
                "description": "Real-time drift detection and automated remediation loop via ServiceNow and GitHub SCuBA.",
                "props": [
                  {
                    "name": "ksi-category",
                    "value": "KSI-UNKNOWN"
                  },
                  {
                    "name": "cisa-maturity",
                    "value": "Optimal"
                  },
                  {
                    "name": "evidence-source",
                    "value": "N/A"
                  }
                ],
                "remarks": "Implemented by Telemetry Control Plane"
              }
            ]
          },
          {
            "uuid": "c0fd53b9-9466-4580-a61e-0cef35b5ec78",
            "source": "https://github.com/GSA/fedramp-automation/raw/main/dist/content/rev5/baselines/json/FedRAMP_rev5_MODERATE-baseline_profile.json",
            "description": "Control implementations for Telemetry Control Plane",
            "implemented-requirements": [
              {
                "uuid": "d114ad29-7c96-4783-8812-57e3f80a592f",
                "control-id": "AC-4",
                "description": "Collapses legacy TIC 2.2 silos into a software-defined, identity-centric perimeter.",
                "props": [
                  {
                    "name": "ksi-category",
                    "value": "KSI-UNKNOWN"
                  },
                  {
                    "name": "cisa-maturity",
                    "value": "Advanced"
                  },
                  {
                    "name": "evidence-source",
                    "value": "N/A"
                  }
                ],
                "remarks": "Implemented by Telemetry Control Plane"
              },
              {
                "uuid": "19e610e5-bb5b-495d-8287-0fb30fb90676",
                "control-id": "SC-38",
                "description": "Collapses legacy TIC 2.2 silos into a software-defined, identity-centric perimeter.",
                "props": [
                  {
                    "name": "ksi-category",
                    "value": "KSI-UNKNOWN"
                  },
                  {
                    "name": "cisa-maturity",
                    "value": "Advanced"
                  },
                  {
                    "name": "evidence-source",
                    "value": "N/A"
                  }
                ],
                "remarks": "Implemented by Telemetry Control Plane"
              }
            ]
          },
          {
            "uuid": "677d1756-ce84-4b87-a1c2-b3c498da9ce8",
            "source": "https://github.com/GSA/fedramp-automation/raw/main/dist/content/rev5/baselines/json/FedRAMP_rev5_MODERATE-baseline_profile.json",
            "description": "Control implementations for Telemetry Control Plane",
            "implemented-requirements": [
              {
                "uuid": "58958c6e-6aed-4b35-9861-c25e7879536a",
                "control-id": "SC-8",
                "description": "Anchors device and user trust to the GSA Federal Root CA with end-to-end channel binding.",
                "props": [
                  {
                    "name": "ksi-category",
                    "value": "KSI-UNKNOWN"
                  },
                  {
                    "name": "cisa-maturity",
                    "value": "Optimal"
                  },
                  {
                    "name": "evidence-source",
                    "value": "N/A"
                  }
                ],
                "remarks": "Implemented by Telemetry Control Plane"
              },
              {
                "uuid": "69032b6a-3a3f-467d-91cc-07ef0807280b",
                "control-id": "IA-3",
                "description": "Anchors device and user trust to the GSA Federal Root CA with end-to-end channel binding.",
                "props": [
                  {
                    "name": "ksi-category",
                    "value": "KSI-UNKNOWN"
                  },
                  {
                    "name": "cisa-maturity",
                    "value": "Optimal"
                  },
                  {
                    "name": "evidence-source",
                    "value": "N/A"
                  }
                ],
                "remarks": "Implemented by Telemetry Control Plane"
              }
            ]
          }
        ]
      },
      {
        "uuid": "6eb3d588-c7a5-4e26-970c-c52416e638d4",
        "type": "service",
        "title": "Endpoint Control Plane",
        "description": "The identity-anchored, telemetry-driven governance layer for all devices",
        "props": [
          {
            "name": "uiao-pillar",
            "value": "ENDPOINT"
          },
          {
            "name": "subtitle",
            "value": "Identity-anchored, telemetry-driven device governance"
          },
          {
            "name": "component-id",
            "value": "component-endpoint"
          }
        ],
        "remarks": "[{\"name\": \"Endpoint Detection Platform\", \"role\": \"Endpoint detection and response\", \"capabilities\": []}, {\"name\": \"Endpoint Management Platform\", \"role\": \"Configuration and compliance management\", \"capabilities\": []}, {\"name\": \"Identity Provider Device Objects\", \"role\": \"Device identity anchoring\", \"capabilities\": []}]",
        "control-implementations": [
          {
            "uuid": "f7fbfdf9-9cf4-4df9-9ea8-bdb6da89d495",
            "source": "https://github.com/GSA/fedramp-automation/raw/main/dist/content/rev5/baselines/json/FedRAMP_rev5_MODERATE-baseline_profile.json",
            "description": "Control implementations for Endpoint Control Plane",
            "implemented-requirements": [
              {
                "uuid": "165c8613-72a9-4e84-9b26-27f4cc84e875",
                "control-id": "IA-2",
                "description": "Enforces phishing-resistant MFA and deterministic Identity-to-IP binding for all US-based endpoints via Entra ID and Infoblox.",
                "props": [
                  {
                    "name": "ksi-category",
                    "value": "KSI-UNKNOWN"
                  },
                  {
                    "name": "cisa-maturity",
                    "value": "Advanced"
                  },
                  {
                    "name": "evidence-source",
                    "value": "N/A"
                  }
                ],
                "remarks": "Implemented by Endpoint Control Plane"
              },
              {
                "uuid": "582b2155-cef3-43de-a4d2-4f64cf14ca74",
                "control-id": "IA-5",
                "description": "Enforces phishing-resistant MFA and deterministic Identity-to-IP binding for all US-based endpoints via Entra ID and Infoblox.",
                "props": [
                  {
                    "name": "ksi-category",
                    "value": "KSI-UNKNOWN"
                  },
                  {
                    "name": "cisa-maturity",
                    "value": "Advanced"
                  },
                  {
                    "name": "evidence-source",
                    "value": "N/A"
                  }
                ],
                "remarks": "Implemented by Endpoint Control Plane"
              },
              {
                "uuid": "85dae69d-383d-439a-b568-821284c515f2",
                "control-id": "AC-19",
                "description": "Enforces phishing-resistant MFA and deterministic Identity-to-IP binding for all US-based endpoints via Entra ID and Infoblox.",
                "props": [
                  {
                    "name": "ksi-category",
                    "value": "KSI-UNKNOWN"
                  },
                  {
                    "name": "cisa-maturity",
                    "value": "Advanced"
                  },
                  {
                    "name": "evidence-source",
                    "value": "N/A"
                  }
                ],
                "remarks": "Implemented by Endpoint Control Plane"
              }
            ]
          },
          {
            "uuid": "ab502c18-e055-4c15-8b32-4e2fcf8b0a72",
            "source": "https://github.com/GSA/fedramp-automation/raw/main/dist/content/rev5/baselines/json/FedRAMP_rev5_MODERATE-baseline_profile.json",
            "description": "Control implementations for Endpoint Control Plane",
            "implemented-requirements": [
              {
                "uuid": "7c956710-173d-4df7-905f-81f14f9457e1",
                "control-id": "SC-7",
                "description": "Establishes a cryptographically secured overlay fabric with US-only geography enforcement.",
                "props": [
                  {
                    "name": "ksi-category",
                    "value": "KSI-UNKNOWN"
                  },
                  {
                    "name": "cisa-maturity",
                    "value": "Optimal"
                  },
                  {
                    "name": "evidence-source",
                    "value": "N/A"
                  }
                ],
                "remarks": "Implemented by Endpoint Control Plane"
              },
              {
                "uuid": "8243fd6d-e215-473e-a3c8-9809e556b806",
                "control-id": "SC-8",
                "description": "Establishes a cryptographically secured overlay fabric with US-only geography enforcement.",
                "props": [
                  {
                    "name": "ksi-category",
                    "value": "KSI-UNKNOWN"
                  },
                  {
                    "name": "cisa-maturity",
                    "value": "Optimal"
                  },
                  {
                    "name": "evidence-source",
                    "value": "N/A"
                  }
                ],
                "remarks": "Implemented by Endpoint Control Plane"
              },
              {
                "uuid": "5e2b5ca6-b85c-4230-b17f-61697cf3605e",
                "control-id": "AC-4",
                "description": "Establishes a cryptographically secured overlay fabric with US-only geography enforcement.",
                "props": [
                  {
                    "name": "ksi-category",
                    "value": "KSI-UNKNOWN"
                  },
                  {
                    "name": "cisa-maturity",
                    "value": "Optimal"
                  },
                  {
                    "name": "evidence-source",
                    "value": "N/A"
                  }
                ],
                "remarks": "Implemented by Endpoint Control Plane"
              }
            ]
          },
          {
            "uuid": "7f864092-7a39-4bd7-8370-8bc0d95de263",
            "source": "https://github.com/GSA/fedramp-automation/raw/main/dist/content/rev5/baselines/json/FedRAMP_rev5_MODERATE-baseline_profile.json",
            "description": "Control implementations for Endpoint Control Plane",
            "implemented-requirements": [
              {
                "uuid": "a48a826d-d748-4eeb-9eee-79eb323af5ec",
                "control-id": "CA-7",
                "description": "Real-time drift detection and automated remediation loop via ServiceNow and GitHub SCuBA.",
                "props": [
                  {
                    "name": "ksi-category",
                    "value": "KSI-UNKNOWN"
                  },
                  {
                    "name": "cisa-maturity",
                    "value": "Optimal"
                  },
                  {
                    "name": "evidence-source",
                    "value": "N/A"
                  }
                ],
                "remarks": "Implemented by Endpoint Control Plane"
              },
              {
                "uuid": "62f2172b-15c3-4f5a-8014-a342f5d9748b",
                "control-id": "CM-6",
                "description": "Real-time drift detection and automated remediation loop via ServiceNow and GitHub SCuBA.",
                "props": [
                  {
                    "name": "ksi-category",
                    "value": "KSI-UNKNOWN"
                  },
                  {
                    "name": "cisa-maturity",
                    "value": "Optimal"
                  },
                  {
                    "name": "evidence-source",
                    "value": "N/A"
                  }
                ],
                "remarks": "Implemented by Endpoint Control Plane"
              },
              {
                "uuid": "048749bf-794c-4072-a6ef-b4efd14a6cb4",
                "control-id": "IR-4",
                "description": "Real-time drift detection and automated remediation loop via ServiceNow and GitHub SCuBA.",
                "props": [
                  {
                    "name": "ksi-category",
                    "value": "KSI-UNKNOWN"
                  },
                  {
                    "name": "cisa-maturity",
                    "value": "Optimal"
                  },
                  {
                    "name": "evidence-source",
                    "value": "N/A"
                  }
                ],
                "remarks": "Implemented by Endpoint Control Plane"
              }
            ]
          },
          {
            "uuid": "7b59de05-4068-4ba8-9707-272fe83398da",
            "source": "https://github.com/GSA/fedramp-automation/raw/main/dist/content/rev5/baselines/json/FedRAMP_rev5_MODERATE-baseline_profile.json",
            "description": "Control implementations for Endpoint Control Plane",
            "implemented-requirements": [
              {
                "uuid": "0cf31260-e2d1-48ef-9076-8a5ad0560c4b",
                "control-id": "AC-4",
                "description": "Collapses legacy TIC 2.2 silos into a software-defined, identity-centric perimeter.",
                "props": [
                  {
                    "name": "ksi-category",
                    "value": "KSI-UNKNOWN"
                  },
                  {
                    "name": "cisa-maturity",
                    "value": "Advanced"
                  },
                  {
                    "name": "evidence-source",
                    "value": "N/A"
                  }
                ],
                "remarks": "Implemented by Endpoint Control Plane"
              },
              {
                "uuid": "02050e20-dd53-42cf-a3d3-f9a4ec843dde",
                "control-id": "SC-38",
                "description": "Collapses legacy TIC 2.2 silos into a software-defined, identity-centric perimeter.",
                "props": [
                  {
                    "name": "ksi-category",
                    "value": "KSI-UNKNOWN"
                  },
                  {
                    "name": "cisa-maturity",
                    "value": "Advanced"
                  },
                  {
                    "name": "evidence-source",
                    "value": "N/A"
                  }
                ],
                "remarks": "Implemented by Endpoint Control Plane"
              }
            ]
          },
          {
            "uuid": "f4c36956-c97a-4c80-ad3a-ddeb9c66da58",
            "source": "https://github.com/GSA/fedramp-automation/raw/main/dist/content/rev5/baselines/json/FedRAMP_rev5_MODERATE-baseline_profile.json",
            "description": "Control implementations for Endpoint Control Plane",
            "implemented-requirements": [
              {
                "uuid": "3177a57f-46f3-444d-bc91-077acaedf499",
                "control-id": "SC-8",
                "description": "Anchors device and user trust to the GSA Federal Root CA with end-to-end channel binding.",
                "props": [
                  {
                    "name": "ksi-category",
                    "value": "KSI-UNKNOWN"
                  },
                  {
                    "name": "cisa-maturity",
                    "value": "Optimal"
                  },
                  {
                    "name": "evidence-source",
                    "value": "N/A"
                  }
                ],
                "remarks": "Implemented by Endpoint Control Plane"
              },
              {
                "uuid": "577ba9b9-4faa-4d48-bbab-8f7bf7e0a214",
                "control-id": "IA-3",
                "description": "Anchors device and user trust to the GSA Federal Root CA with end-to-end channel binding.",
                "props": [
                  {
                    "name": "ksi-category",
                    "value": "KSI-UNKNOWN"
                  },
                  {
                    "name": "cisa-maturity",
                    "value": "Optimal"
                  },
                  {
                    "name": "evidence-source",
                    "value": "N/A"
                  }
                ],
                "remarks": "Implemented by Endpoint Control Plane"
              }
            ]
          }
        ]
      },
      {
        "uuid": "8f34bab6-01a4-4d66-9aff-0fa5780b7df1",
        "type": "service",
        "title": "Security Control Plane",
        "description": "The enforcement, validation, and assurance substrate for Zero Trust across all systems, identities, networks, and workloads",
        "props": [
          {
            "name": "uiao-pillar",
            "value": "SECURITY"
          },
          {
            "name": "subtitle",
            "value": "Zero Trust enforcement, validation, and assurance"
          },
          {
            "name": "component-id",
            "value": "component-security"
          }
        ],
        "remarks": "[]",
        "control-implementations": [
          {
            "uuid": "3b955118-9fd4-47ca-9b25-4ffe6b32a2c7",
            "source": "https://github.com/GSA/fedramp-automation/raw/main/dist/content/rev5/baselines/json/FedRAMP_rev5_MODERATE-baseline_profile.json",
            "description": "Control implementations for Security Control Plane",
            "implemented-requirements": [
              {
                "uuid": "7168b922-a62c-4dc7-9e60-a69891ec3554",
                "control-id": "IA-2",
                "description": "Enforces phishing-resistant MFA and deterministic Identity-to-IP binding for all US-based endpoints via Entra ID and Infoblox.",
                "props": [
                  {
                    "name": "ksi-category",
                    "value": "KSI-UNKNOWN"
                  },
                  {
                    "name": "cisa-maturity",
                    "value": "Advanced"
                  },
                  {
                    "name": "evidence-source",
                    "value": "N/A"
                  }
                ],
                "remarks": "Implemented by Security Control Plane"
              },
              {
                "uuid": "dace71ae-d835-4f14-a051-9876505ed53d",
                "control-id": "IA-5",
                "description": "Enforces phishing-resistant MFA and deterministic Identity-to-IP binding for all US-based endpoints via Entra ID and Infoblox.",
                "props": [
                  {
                    "name": "ksi-category",
                    "value": "KSI-UNKNOWN"
                  },
                  {
                    "name": "cisa-maturity",
                    "value": "Advanced"
                  },
                  {
                    "name": "evidence-source",
                    "value": "N/A"
                  }
                ],
                "remarks": "Implemented by Security Control Plane"
              },
              {
                "uuid": "c9378781-bf93-49a3-9be9-c56c9e7b4b46",
                "control-id": "AC-19",
                "description": "Enforces phishing-resistant MFA and deterministic Identity-to-IP binding for all US-based endpoints via Entra ID and Infoblox.",
                "props": [
                  {
                    "name": "ksi-category",
                    "value": "KSI-UNKNOWN"
                  },
                  {
                    "name": "cisa-maturity",
                    "value": "Advanced"
                  },
                  {
                    "name": "evidence-source",
                    "value": "N/A"
                  }
                ],
                "remarks": "Implemented by Security Control Plane"
              }
            ]
          },
          {
            "uuid": "c48b9719-9548-4497-b548-72810474c600",
            "source": "https://github.com/GSA/fedramp-automation/raw/main/dist/content/rev5/baselines/json/FedRAMP_rev5_MODERATE-baseline_profile.json",
            "description": "Control implementations for Security Control Plane",
            "implemented-requirements": [
              {
                "uuid": "09931700-847c-4737-9fd3-fc533099c312",
                "control-id": "SC-7",
                "description": "Establishes a cryptographically secured overlay fabric with US-only geography enforcement.",
                "props": [
                  {
                    "name": "ksi-category",
                    "value": "KSI-UNKNOWN"
                  },
                  {
                    "name": "cisa-maturity",
                    "value": "Optimal"
                  },
                  {
                    "name": "evidence-source",
                    "value": "N/A"
                  }
                ],
                "remarks": "Implemented by Security Control Plane"
              },
              {
                "uuid": "1ab36a6e-f790-43d8-9746-d6d236a117ee",
                "control-id": "SC-8",
                "description": "Establishes a cryptographically secured overlay fabric with US-only geography enforcement.",
                "props": [
                  {
                    "name": "ksi-category",
                    "value": "KSI-UNKNOWN"
                  },
                  {
                    "name": "cisa-maturity",
                    "value": "Optimal"
                  },
                  {
                    "name": "evidence-source",
                    "value": "N/A"
                  }
                ],
                "remarks": "Implemented by Security Control Plane"
              },
              {
                "uuid": "6bd43f10-2368-4e23-bac4-ce2076b90b5b",
                "control-id": "AC-4",
                "description": "Establishes a cryptographically secured overlay fabric with US-only geography enforcement.",
                "props": [
                  {
                    "name": "ksi-category",
                    "value": "KSI-UNKNOWN"
                  },
                  {
                    "name": "cisa-maturity",
                    "value": "Optimal"
                  },
                  {
                    "name": "evidence-source",
                    "value": "N/A"
                  }
                ],
                "remarks": "Implemented by Security Control Plane"
              }
            ]
          },
          {
            "uuid": "334c00b0-ad90-4e5f-87e5-669c758cfc7d",
            "source": "https://github.com/GSA/fedramp-automation/raw/main/dist/content/rev5/baselines/json/FedRAMP_rev5_MODERATE-baseline_profile.json",
            "description": "Control implementations for Security Control Plane",
            "implemented-requirements": [
              {
                "uuid": "99e4f328-5579-4c17-baf0-ec2ff8a99ce0",
                "control-id": "CA-7",
                "description": "Real-time drift detection and automated remediation loop via ServiceNow and GitHub SCuBA.",
                "props": [
                  {
                    "name": "ksi-category",
                    "value": "KSI-UNKNOWN"
                  },
                  {
                    "name": "cisa-maturity",
                    "value": "Optimal"
                  },
                  {
                    "name": "evidence-source",
                    "value": "N/A"
                  }
                ],
                "remarks": "Implemented by Security Control Plane"
              },
              {
                "uuid": "ca3c194a-00e1-469f-aec4-7fe8896a5df9",
                "control-id": "CM-6",
                "description": "Real-time drift detection and automated remediation loop via ServiceNow and GitHub SCuBA.",
                "props": [
                  {
                    "name": "ksi-category",
                    "value": "KSI-UNKNOWN"
                  },
                  {
                    "name": "cisa-maturity",
                    "value": "Optimal"
                  },
                  {
                    "name": "evidence-source",
                    "value": "N/A"
                  }
                ],
                "remarks": "Implemented by Security Control Plane"
              },
              {
                "uuid": "0a76784b-c987-472a-8b28-5e1664db64f6",
                "control-id": "IR-4",
                "description": "Real-time drift detection and automated remediation loop via ServiceNow and GitHub SCuBA.",
                "props": [
                  {
                    "name": "ksi-category",
                    "value": "KSI-UNKNOWN"
                  },
                  {
                    "name": "cisa-maturity",
                    "value": "Optimal"
                  },
                  {
                    "name": "evidence-source",
                    "value": "N/A"
                  }
                ],
                "remarks": "Implemented by Security Control Plane"
              }
            ]
          },
          {
            "uuid": "d4aff847-29e7-4a49-b0d4-4469f76906d9",
            "source": "https://github.com/GSA/fedramp-automation/raw/main/dist/content/rev5/baselines/json/FedRAMP_rev5_MODERATE-baseline_profile.json",
            "description": "Control implementations for Security Control Plane",
            "implemented-requirements": [
              {
                "uuid": "ddb98aa4-698e-4074-b47b-de922e4d1c88",
                "control-id": "AC-4",
                "description": "Collapses legacy TIC 2.2 silos into a software-defined, identity-centric perimeter.",
                "props": [
                  {
                    "name": "ksi-category",
                    "value": "KSI-UNKNOWN"
                  },
                  {
                    "name": "cisa-maturity",
                    "value": "Advanced"
                  },
                  {
                    "name": "evidence-source",
                    "value": "N/A"
                  }
                ],
                "remarks": "Implemented by Security Control Plane"
              },
              {
                "uuid": "61ef376e-57bf-4155-915d-0e6b331164a9",
                "control-id": "SC-38",
                "description": "Collapses legacy TIC 2.2 silos into a software-defined, identity-centric perimeter.",
                "props": [
                  {
                    "name": "ksi-category",
                    "value": "KSI-UNKNOWN"
                  },
                  {
                    "name": "cisa-maturity",
                    "value": "Advanced"
                  },
                  {
                    "name": "evidence-source",
                    "value": "N/A"
                  }
                ],
                "remarks": "Implemented by Security Control Plane"
              }
            ]
          },
          {
            "uuid": "f5b51b1f-9a95-47df-bfb7-cd4e2471c3bd",
            "source": "https://github.com/GSA/fedramp-automation/raw/main/dist/content/rev5/baselines/json/FedRAMP_rev5_MODERATE-baseline_profile.json",
            "description": "Control implementations for Security Control Plane",
            "implemented-requirements": [
              {
                "uuid": "40f60dbc-f752-48b7-a7d8-a35e77bb4063",
                "control-id": "SC-8",
                "description": "Anchors device and user trust to the GSA Federal Root CA with end-to-end channel binding.",
                "props": [
                  {
                    "name": "ksi-category",
                    "value": "KSI-UNKNOWN"
                  },
                  {
                    "name": "cisa-maturity",
                    "value": "Optimal"
                  },
                  {
                    "name": "evidence-source",
                    "value": "N/A"
                  }
                ],
                "remarks": "Implemented by Security Control Plane"
              },
              {
                "uuid": "1ec1340e-e0a4-4e56-887b-32fc49ade446",
                "control-id": "IA-3",
                "description": "Anchors device and user trust to the GSA Federal Root CA with end-to-end channel binding.",
                "props": [
                  {
                    "name": "ksi-category",
                    "value": "KSI-UNKNOWN"
                  },
                  {
                    "name": "cisa-maturity",
                    "value": "Optimal"
                  },
                  {
                    "name": "evidence-source",
                    "value": "N/A"
                  }
                ],
                "remarks": "Implemented by Security Control Plane"
              }
            ]
          }
        ]
      }
    ],
    "capabilities": []
  }
}