{
  "component-definition": {
    "uuid": "6ca743f9-7977-4b1f-93a8-f5747bda5153",
    "metadata": {
      "title": "UIAO Unified Identity-Addressing-Overlay Architecture",
      "version": "1.0",
      "oscal-version": "1.0.4",
      "last-modified": "2026-03-31T17:33:53.488658Z",
      "published": "2026-03-31T17:33:53.488658Z",
      "props": [
        {
          "name": "fedramp-impact",
          "value": "Moderate",
          "ns": "https://fedramp.gov/ns/oscal"
        },
        {
          "name": "compliance-strategy",
          "value": "OSCAL-based Telemetry Validation",
          "ns": "https://fedramp.gov/ns/oscal"
        },
        {
          "name": "ksi-dashboard",
          "value": "Operational"
        },
        {
          "name": "framework-version",
          "value": "2026.1"
        },
        {
          "name": "markup-type",
          "value": "json",
          "ns": "https://fedramp.gov/ns/oscal"
        }
      ]
    },
    "components": [
      {
        "uuid": "77d4639d-acf0-4f15-bfe1-526dbd22d706",
        "type": "service",
        "title": "Identity Control Plane",
        "description": "The authoritative identity control plane for the Unified Modernization Program",
        "props": [
          {
            "name": "uiao-pillar",
            "value": "IDENTITY"
          },
          {
            "name": "subtitle",
            "value": "Identity Provider + ICAM + Zero Trust"
          },
          {
            "name": "component-id",
            "value": "component-identity"
          }
        ],
        "remarks": "[{\"name\": \"Identity Provider\", \"role\": \"Primary Identity Provider\", \"capabilities\": [\"Conditional Access (CA)\", \"MFA / SSPR\", \"Identity Protection\", \"Authentication Strength\"]}, {\"name\": \"ICAM Governance\", \"role\": \"Identity governance and compliance\", \"capabilities\": [\"NIST 800-63 Alignment\", \"OMB M-19-17 Compliance\", \"Credentialing\", \"Access Reviews\", \"Privileged Identity Management (PIM)\", \"Joiner/Mover/Leaver Automation\"]}, {\"name\": \"Zero Trust Policy Engine\", \"role\": \"Continuous access evaluation\", \"capabilities\": [\"Identity + Device + Location + Risk\", \"Continuous Access Evaluation (CAE)\", \"Policy decisions exported to SD-WAN + Telemetry\"]}]",
        "control-implementations": [
          {
            "uuid": "192f4e2d-1ef5-4f06-9915-f4e6ceb78bcf",
            "source": "https://github.com/GSA/fedramp-automation/raw/main/dist/content/rev5/baselines/json/FedRAMP_rev5_MODERATE-baseline_profile.json",
            "description": "Control implementations for Identity Control Plane",
            "implemented-requirements": [
              {
                "uuid": "5d93b74d-4d87-4df8-859a-3d979691fb9e",
                "control-id": "IA-2",
                "description": "Enforces phishing-resistant MFA and deterministic Identity-to-IP binding for all US-based endpoints via Entra ID and Infoblox.",
                "props": [
                  {
                    "name": "ksi-category",
                    "value": "KSI-UNKNOWN"
                  },
                  {
                    "name": "cisa-maturity",
                    "value": "Advanced"
                  },
                  {
                    "name": "evidence-source",
                    "value": "N/A"
                  }
                ],
                "remarks": "Implemented by Identity Control Plane"
              },
              {
                "uuid": "2d88213d-e23d-49e6-8378-3ed6517b30b8",
                "control-id": "IA-5",
                "description": "Enforces phishing-resistant MFA and deterministic Identity-to-IP binding for all US-based endpoints via Entra ID and Infoblox.",
                "props": [
                  {
                    "name": "ksi-category",
                    "value": "KSI-UNKNOWN"
                  },
                  {
                    "name": "cisa-maturity",
                    "value": "Advanced"
                  },
                  {
                    "name": "evidence-source",
                    "value": "N/A"
                  }
                ],
                "remarks": "Implemented by Identity Control Plane"
              },
              {
                "uuid": "7f0846ec-2247-4a02-be62-b2add90f4b7b",
                "control-id": "AC-19",
                "description": "Enforces phishing-resistant MFA and deterministic Identity-to-IP binding for all US-based endpoints via Entra ID and Infoblox.",
                "props": [
                  {
                    "name": "ksi-category",
                    "value": "KSI-UNKNOWN"
                  },
                  {
                    "name": "cisa-maturity",
                    "value": "Advanced"
                  },
                  {
                    "name": "evidence-source",
                    "value": "N/A"
                  }
                ],
                "remarks": "Implemented by Identity Control Plane"
              }
            ]
          },
          {
            "uuid": "0ccd6d97-eeae-48b2-b009-002df9015077",
            "source": "https://github.com/GSA/fedramp-automation/raw/main/dist/content/rev5/baselines/json/FedRAMP_rev5_MODERATE-baseline_profile.json",
            "description": "Control implementations for Identity Control Plane",
            "implemented-requirements": [
              {
                "uuid": "ab25efa0-49cf-4081-94cd-ff14e1023b98",
                "control-id": "SC-7",
                "description": "Establishes a cryptographically secured overlay fabric with US-only geography enforcement.",
                "props": [
                  {
                    "name": "ksi-category",
                    "value": "KSI-UNKNOWN"
                  },
                  {
                    "name": "cisa-maturity",
                    "value": "Optimal"
                  },
                  {
                    "name": "evidence-source",
                    "value": "N/A"
                  }
                ],
                "remarks": "Implemented by Identity Control Plane"
              },
              {
                "uuid": "8b3b7334-9a94-493a-9cea-8f1ba1e079ae",
                "control-id": "SC-8",
                "description": "Establishes a cryptographically secured overlay fabric with US-only geography enforcement.",
                "props": [
                  {
                    "name": "ksi-category",
                    "value": "KSI-UNKNOWN"
                  },
                  {
                    "name": "cisa-maturity",
                    "value": "Optimal"
                  },
                  {
                    "name": "evidence-source",
                    "value": "N/A"
                  }
                ],
                "remarks": "Implemented by Identity Control Plane"
              },
              {
                "uuid": "aa73114c-8159-4f54-9220-9b9c09863219",
                "control-id": "AC-4",
                "description": "Establishes a cryptographically secured overlay fabric with US-only geography enforcement.",
                "props": [
                  {
                    "name": "ksi-category",
                    "value": "KSI-UNKNOWN"
                  },
                  {
                    "name": "cisa-maturity",
                    "value": "Optimal"
                  },
                  {
                    "name": "evidence-source",
                    "value": "N/A"
                  }
                ],
                "remarks": "Implemented by Identity Control Plane"
              }
            ]
          },
          {
            "uuid": "8a7d99d0-3393-425b-a5d4-3cb5d3803b34",
            "source": "https://github.com/GSA/fedramp-automation/raw/main/dist/content/rev5/baselines/json/FedRAMP_rev5_MODERATE-baseline_profile.json",
            "description": "Control implementations for Identity Control Plane",
            "implemented-requirements": [
              {
                "uuid": "76db5524-4025-4c78-a986-f1437837bcc1",
                "control-id": "CA-7",
                "description": "Real-time drift detection and automated remediation loop via ServiceNow and GitHub SCuBA.",
                "props": [
                  {
                    "name": "ksi-category",
                    "value": "KSI-UNKNOWN"
                  },
                  {
                    "name": "cisa-maturity",
                    "value": "Optimal"
                  },
                  {
                    "name": "evidence-source",
                    "value": "N/A"
                  }
                ],
                "remarks": "Implemented by Identity Control Plane"
              },
              {
                "uuid": "da9f0812-8e0b-4afc-85ca-e13f193d7640",
                "control-id": "CM-6",
                "description": "Real-time drift detection and automated remediation loop via ServiceNow and GitHub SCuBA.",
                "props": [
                  {
                    "name": "ksi-category",
                    "value": "KSI-UNKNOWN"
                  },
                  {
                    "name": "cisa-maturity",
                    "value": "Optimal"
                  },
                  {
                    "name": "evidence-source",
                    "value": "N/A"
                  }
                ],
                "remarks": "Implemented by Identity Control Plane"
              },
              {
                "uuid": "e0c27a59-e175-4259-946a-12a468dfa6b4",
                "control-id": "IR-4",
                "description": "Real-time drift detection and automated remediation loop via ServiceNow and GitHub SCuBA.",
                "props": [
                  {
                    "name": "ksi-category",
                    "value": "KSI-UNKNOWN"
                  },
                  {
                    "name": "cisa-maturity",
                    "value": "Optimal"
                  },
                  {
                    "name": "evidence-source",
                    "value": "N/A"
                  }
                ],
                "remarks": "Implemented by Identity Control Plane"
              }
            ]
          },
          {
            "uuid": "5f28381e-c141-4249-8c08-314f0c81719e",
            "source": "https://github.com/GSA/fedramp-automation/raw/main/dist/content/rev5/baselines/json/FedRAMP_rev5_MODERATE-baseline_profile.json",
            "description": "Control implementations for Identity Control Plane",
            "implemented-requirements": [
              {
                "uuid": "00016cb9-647d-482b-a486-696ae8c01719",
                "control-id": "AC-4",
                "description": "Collapses legacy TIC 2.2 silos into a software-defined, identity-centric perimeter.",
                "props": [
                  {
                    "name": "ksi-category",
                    "value": "KSI-UNKNOWN"
                  },
                  {
                    "name": "cisa-maturity",
                    "value": "Advanced"
                  },
                  {
                    "name": "evidence-source",
                    "value": "N/A"
                  }
                ],
                "remarks": "Implemented by Identity Control Plane"
              },
              {
                "uuid": "9978f4b4-c62e-4a8e-9274-eaaea43c7c84",
                "control-id": "SC-38",
                "description": "Collapses legacy TIC 2.2 silos into a software-defined, identity-centric perimeter.",
                "props": [
                  {
                    "name": "ksi-category",
                    "value": "KSI-UNKNOWN"
                  },
                  {
                    "name": "cisa-maturity",
                    "value": "Advanced"
                  },
                  {
                    "name": "evidence-source",
                    "value": "N/A"
                  }
                ],
                "remarks": "Implemented by Identity Control Plane"
              }
            ]
          },
          {
            "uuid": "0f77d2f1-4002-4352-bc7e-ad83153ce4b5",
            "source": "https://github.com/GSA/fedramp-automation/raw/main/dist/content/rev5/baselines/json/FedRAMP_rev5_MODERATE-baseline_profile.json",
            "description": "Control implementations for Identity Control Plane",
            "implemented-requirements": [
              {
                "uuid": "07c3aa25-0a9b-4bdc-a0cd-683864a9f406",
                "control-id": "SC-8",
                "description": "Anchors device and user trust to the GSA Federal Root CA with end-to-end channel binding.",
                "props": [
                  {
                    "name": "ksi-category",
                    "value": "KSI-UNKNOWN"
                  },
                  {
                    "name": "cisa-maturity",
                    "value": "Optimal"
                  },
                  {
                    "name": "evidence-source",
                    "value": "N/A"
                  }
                ],
                "remarks": "Implemented by Identity Control Plane"
              },
              {
                "uuid": "4ec1757f-119d-4af6-9b16-60b202350a50",
                "control-id": "IA-3",
                "description": "Anchors device and user trust to the GSA Federal Root CA with end-to-end channel binding.",
                "props": [
                  {
                    "name": "ksi-category",
                    "value": "KSI-UNKNOWN"
                  },
                  {
                    "name": "cisa-maturity",
                    "value": "Optimal"
                  },
                  {
                    "name": "evidence-source",
                    "value": "N/A"
                  }
                ],
                "remarks": "Implemented by Identity Control Plane"
              }
            ]
          }
        ]
      },
      {
        "uuid": "61a997ad-935a-46fe-9229-5f103e171900",
        "type": "service",
        "title": "Addressing Control Plane",
        "description": "The authoritative source of truth for identity-anchored addressing, DNS, DHCP, and cross-cloud reconciliation",
        "props": [
          {
            "name": "uiao-pillar",
            "value": "ADDRESSING"
          },
          {
            "name": "subtitle",
            "value": "IPAM Platform"
          },
          {
            "name": "component-id",
            "value": "component-addressing"
          }
        ],
        "remarks": "[{\"name\": \"IPAM Platform\", \"role\": \"Authoritative Source of Truth\", \"capabilities\": [\"IP address allocation and tracking\", \"Subnet creation and lifecycle management\", \"DNS zone management and record authority\", \"DHCP scope governance and lease evidence\"]}, {\"name\": \"DNS Management\", \"role\": \"Authoritative DNS zones\", \"capabilities\": [\"Internal zones managed by IPAM platform\", \"Split-horizon DNS\", \"DNS evidence tied to identity/subnet/location\"]}, {\"name\": \"DHCP Management\", \"role\": \"Scope governance\", \"capabilities\": [\"Scopes defined and owned by IPAM\", \"Lease durations aligned with device identity\", \"Automatic DNS record creation from DHCP leases\"]}, {\"name\": \"Cloud IPAM Reconciliation\", \"role\": \"Multi-cloud addressing truth\", \"capabilities\": []}]",
        "control-implementations": [
          {
            "uuid": "20815447-04f1-4d34-93a0-3371ee9cd7f6",
            "source": "https://github.com/GSA/fedramp-automation/raw/main/dist/content/rev5/baselines/json/FedRAMP_rev5_MODERATE-baseline_profile.json",
            "description": "Control implementations for Addressing Control Plane",
            "implemented-requirements": [
              {
                "uuid": "79b38f7d-0472-4d4b-98c9-cafecac6493f",
                "control-id": "IA-2",
                "description": "Enforces phishing-resistant MFA and deterministic Identity-to-IP binding for all US-based endpoints via Entra ID and Infoblox.",
                "props": [
                  {
                    "name": "ksi-category",
                    "value": "KSI-UNKNOWN"
                  },
                  {
                    "name": "cisa-maturity",
                    "value": "Advanced"
                  },
                  {
                    "name": "evidence-source",
                    "value": "N/A"
                  }
                ],
                "remarks": "Implemented by Addressing Control Plane"
              },
              {
                "uuid": "6b460206-bee3-4d6e-a41e-1c1b36e41a5a",
                "control-id": "IA-5",
                "description": "Enforces phishing-resistant MFA and deterministic Identity-to-IP binding for all US-based endpoints via Entra ID and Infoblox.",
                "props": [
                  {
                    "name": "ksi-category",
                    "value": "KSI-UNKNOWN"
                  },
                  {
                    "name": "cisa-maturity",
                    "value": "Advanced"
                  },
                  {
                    "name": "evidence-source",
                    "value": "N/A"
                  }
                ],
                "remarks": "Implemented by Addressing Control Plane"
              },
              {
                "uuid": "d927bc51-12b6-4d31-8f80-478b761b92e6",
                "control-id": "AC-19",
                "description": "Enforces phishing-resistant MFA and deterministic Identity-to-IP binding for all US-based endpoints via Entra ID and Infoblox.",
                "props": [
                  {
                    "name": "ksi-category",
                    "value": "KSI-UNKNOWN"
                  },
                  {
                    "name": "cisa-maturity",
                    "value": "Advanced"
                  },
                  {
                    "name": "evidence-source",
                    "value": "N/A"
                  }
                ],
                "remarks": "Implemented by Addressing Control Plane"
              }
            ]
          },
          {
            "uuid": "ad36ebaa-707d-450a-826b-66e879af6698",
            "source": "https://github.com/GSA/fedramp-automation/raw/main/dist/content/rev5/baselines/json/FedRAMP_rev5_MODERATE-baseline_profile.json",
            "description": "Control implementations for Addressing Control Plane",
            "implemented-requirements": [
              {
                "uuid": "25540e8a-da8f-4562-bc16-c5e9f7d527d8",
                "control-id": "SC-7",
                "description": "Establishes a cryptographically secured overlay fabric with US-only geography enforcement.",
                "props": [
                  {
                    "name": "ksi-category",
                    "value": "KSI-UNKNOWN"
                  },
                  {
                    "name": "cisa-maturity",
                    "value": "Optimal"
                  },
                  {
                    "name": "evidence-source",
                    "value": "N/A"
                  }
                ],
                "remarks": "Implemented by Addressing Control Plane"
              },
              {
                "uuid": "b8571765-5601-430b-a9cb-6f123ed2b76c",
                "control-id": "SC-8",
                "description": "Establishes a cryptographically secured overlay fabric with US-only geography enforcement.",
                "props": [
                  {
                    "name": "ksi-category",
                    "value": "KSI-UNKNOWN"
                  },
                  {
                    "name": "cisa-maturity",
                    "value": "Optimal"
                  },
                  {
                    "name": "evidence-source",
                    "value": "N/A"
                  }
                ],
                "remarks": "Implemented by Addressing Control Plane"
              },
              {
                "uuid": "409b1b18-3209-49f0-922e-f8fd60386801",
                "control-id": "AC-4",
                "description": "Establishes a cryptographically secured overlay fabric with US-only geography enforcement.",
                "props": [
                  {
                    "name": "ksi-category",
                    "value": "KSI-UNKNOWN"
                  },
                  {
                    "name": "cisa-maturity",
                    "value": "Optimal"
                  },
                  {
                    "name": "evidence-source",
                    "value": "N/A"
                  }
                ],
                "remarks": "Implemented by Addressing Control Plane"
              }
            ]
          },
          {
            "uuid": "d0778a7f-5812-4931-ad47-1a77df4467c4",
            "source": "https://github.com/GSA/fedramp-automation/raw/main/dist/content/rev5/baselines/json/FedRAMP_rev5_MODERATE-baseline_profile.json",
            "description": "Control implementations for Addressing Control Plane",
            "implemented-requirements": [
              {
                "uuid": "7d2ed10b-3c4c-41e2-8563-345b86e57154",
                "control-id": "CA-7",
                "description": "Real-time drift detection and automated remediation loop via ServiceNow and GitHub SCuBA.",
                "props": [
                  {
                    "name": "ksi-category",
                    "value": "KSI-UNKNOWN"
                  },
                  {
                    "name": "cisa-maturity",
                    "value": "Optimal"
                  },
                  {
                    "name": "evidence-source",
                    "value": "N/A"
                  }
                ],
                "remarks": "Implemented by Addressing Control Plane"
              },
              {
                "uuid": "259e893f-52c8-4387-8b95-6cfb412ae177",
                "control-id": "CM-6",
                "description": "Real-time drift detection and automated remediation loop via ServiceNow and GitHub SCuBA.",
                "props": [
                  {
                    "name": "ksi-category",
                    "value": "KSI-UNKNOWN"
                  },
                  {
                    "name": "cisa-maturity",
                    "value": "Optimal"
                  },
                  {
                    "name": "evidence-source",
                    "value": "N/A"
                  }
                ],
                "remarks": "Implemented by Addressing Control Plane"
              },
              {
                "uuid": "715a35ef-de1c-41d9-b1de-ede87f297fbe",
                "control-id": "IR-4",
                "description": "Real-time drift detection and automated remediation loop via ServiceNow and GitHub SCuBA.",
                "props": [
                  {
                    "name": "ksi-category",
                    "value": "KSI-UNKNOWN"
                  },
                  {
                    "name": "cisa-maturity",
                    "value": "Optimal"
                  },
                  {
                    "name": "evidence-source",
                    "value": "N/A"
                  }
                ],
                "remarks": "Implemented by Addressing Control Plane"
              }
            ]
          },
          {
            "uuid": "5117b7e6-4864-41f5-8147-d4b427c86e12",
            "source": "https://github.com/GSA/fedramp-automation/raw/main/dist/content/rev5/baselines/json/FedRAMP_rev5_MODERATE-baseline_profile.json",
            "description": "Control implementations for Addressing Control Plane",
            "implemented-requirements": [
              {
                "uuid": "0abfeaaf-19b6-4a6a-81e9-218467dd40e1",
                "control-id": "AC-4",
                "description": "Collapses legacy TIC 2.2 silos into a software-defined, identity-centric perimeter.",
                "props": [
                  {
                    "name": "ksi-category",
                    "value": "KSI-UNKNOWN"
                  },
                  {
                    "name": "cisa-maturity",
                    "value": "Advanced"
                  },
                  {
                    "name": "evidence-source",
                    "value": "N/A"
                  }
                ],
                "remarks": "Implemented by Addressing Control Plane"
              },
              {
                "uuid": "29c5f858-066a-48a0-a644-c35b39c08c63",
                "control-id": "SC-38",
                "description": "Collapses legacy TIC 2.2 silos into a software-defined, identity-centric perimeter.",
                "props": [
                  {
                    "name": "ksi-category",
                    "value": "KSI-UNKNOWN"
                  },
                  {
                    "name": "cisa-maturity",
                    "value": "Advanced"
                  },
                  {
                    "name": "evidence-source",
                    "value": "N/A"
                  }
                ],
                "remarks": "Implemented by Addressing Control Plane"
              }
            ]
          },
          {
            "uuid": "573c383a-92fb-44d6-a587-7b4c05003852",
            "source": "https://github.com/GSA/fedramp-automation/raw/main/dist/content/rev5/baselines/json/FedRAMP_rev5_MODERATE-baseline_profile.json",
            "description": "Control implementations for Addressing Control Plane",
            "implemented-requirements": [
              {
                "uuid": "49fc05aa-dbe1-43a4-9b2d-79255e0b64c9",
                "control-id": "SC-8",
                "description": "Anchors device and user trust to the GSA Federal Root CA with end-to-end channel binding.",
                "props": [
                  {
                    "name": "ksi-category",
                    "value": "KSI-UNKNOWN"
                  },
                  {
                    "name": "cisa-maturity",
                    "value": "Optimal"
                  },
                  {
                    "name": "evidence-source",
                    "value": "N/A"
                  }
                ],
                "remarks": "Implemented by Addressing Control Plane"
              },
              {
                "uuid": "4debe004-ab54-4692-a87c-994ebf7f3b22",
                "control-id": "IA-3",
                "description": "Anchors device and user trust to the GSA Federal Root CA with end-to-end channel binding.",
                "props": [
                  {
                    "name": "ksi-category",
                    "value": "KSI-UNKNOWN"
                  },
                  {
                    "name": "cisa-maturity",
                    "value": "Optimal"
                  },
                  {
                    "name": "evidence-source",
                    "value": "N/A"
                  }
                ],
                "remarks": "Implemented by Addressing Control Plane"
              }
            ]
          }
        ]
      },
      {
        "uuid": "70923e85-c8eb-4cff-a7ae-7996d84ad78a",
        "type": "service",
        "title": "Network Control Plane",
        "description": "A governed, identity-anchored, telemetry-driven routing and segmentation system",
        "props": [
          {
            "name": "uiao-pillar",
            "value": "NETWORK"
          },
          {
            "name": "subtitle",
            "value": "SD-WAN Platform"
          },
          {
            "name": "component-id",
            "value": "component-network"
          }
        ],
        "remarks": "[{\"name\": \"SD-WAN Policy Engine\", \"role\": \"Centralized policy engine\", \"capabilities\": [\"Pushes routing/segmentation/security policies to WAN edges\", \"Integrates with identity and telemetry for INR\"]}, {\"name\": \"SD-WAN Control Orchestrator\", \"role\": \"Control-plane orchestrator\", \"capabilities\": [\"OMP route distribution\", \"Security and segmentation policy distribution\"]}, {\"name\": \"SD-WAN Orchestration Controller\", \"role\": \"Secure orchestration\", \"capabilities\": [\"Secure control-plane connections\", \"WAN edge device authentication\"]}, {\"name\": \"WAN Edge Devices\", \"role\": \"Enforcement points\", \"capabilities\": [\"Segmentation and routing enforcement\", \"IPSEC/GRE overlay maintenance\", \"Telemetry emission\"]}]",
        "control-implementations": [
          {
            "uuid": "6c72fbc8-c057-4e66-a2f6-888808ed0e15",
            "source": "https://github.com/GSA/fedramp-automation/raw/main/dist/content/rev5/baselines/json/FedRAMP_rev5_MODERATE-baseline_profile.json",
            "description": "Control implementations for Network Control Plane",
            "implemented-requirements": [
              {
                "uuid": "8f8026fa-e658-4d06-8f4d-f73495f89dec",
                "control-id": "IA-2",
                "description": "Enforces phishing-resistant MFA and deterministic Identity-to-IP binding for all US-based endpoints via Entra ID and Infoblox.",
                "props": [
                  {
                    "name": "ksi-category",
                    "value": "KSI-UNKNOWN"
                  },
                  {
                    "name": "cisa-maturity",
                    "value": "Advanced"
                  },
                  {
                    "name": "evidence-source",
                    "value": "N/A"
                  }
                ],
                "remarks": "Implemented by Network Control Plane"
              },
              {
                "uuid": "7784e39f-2bfd-4add-96a2-804a276849f9",
                "control-id": "IA-5",
                "description": "Enforces phishing-resistant MFA and deterministic Identity-to-IP binding for all US-based endpoints via Entra ID and Infoblox.",
                "props": [
                  {
                    "name": "ksi-category",
                    "value": "KSI-UNKNOWN"
                  },
                  {
                    "name": "cisa-maturity",
                    "value": "Advanced"
                  },
                  {
                    "name": "evidence-source",
                    "value": "N/A"
                  }
                ],
                "remarks": "Implemented by Network Control Plane"
              },
              {
                "uuid": "4a23943d-ce30-46e9-b13c-71ce03bea4f0",
                "control-id": "AC-19",
                "description": "Enforces phishing-resistant MFA and deterministic Identity-to-IP binding for all US-based endpoints via Entra ID and Infoblox.",
                "props": [
                  {
                    "name": "ksi-category",
                    "value": "KSI-UNKNOWN"
                  },
                  {
                    "name": "cisa-maturity",
                    "value": "Advanced"
                  },
                  {
                    "name": "evidence-source",
                    "value": "N/A"
                  }
                ],
                "remarks": "Implemented by Network Control Plane"
              }
            ]
          },
          {
            "uuid": "2cda0993-a7e7-4874-afd2-fdba9af97ec0",
            "source": "https://github.com/GSA/fedramp-automation/raw/main/dist/content/rev5/baselines/json/FedRAMP_rev5_MODERATE-baseline_profile.json",
            "description": "Control implementations for Network Control Plane",
            "implemented-requirements": [
              {
                "uuid": "2dc5c279-c5c9-446c-84c8-c7d1b8fe1823",
                "control-id": "SC-7",
                "description": "Establishes a cryptographically secured overlay fabric with US-only geography enforcement.",
                "props": [
                  {
                    "name": "ksi-category",
                    "value": "KSI-UNKNOWN"
                  },
                  {
                    "name": "cisa-maturity",
                    "value": "Optimal"
                  },
                  {
                    "name": "evidence-source",
                    "value": "N/A"
                  }
                ],
                "remarks": "Implemented by Network Control Plane"
              },
              {
                "uuid": "b2bfa5a3-9bdc-49c0-81ff-bb4d45b3b0bd",
                "control-id": "SC-8",
                "description": "Establishes a cryptographically secured overlay fabric with US-only geography enforcement.",
                "props": [
                  {
                    "name": "ksi-category",
                    "value": "KSI-UNKNOWN"
                  },
                  {
                    "name": "cisa-maturity",
                    "value": "Optimal"
                  },
                  {
                    "name": "evidence-source",
                    "value": "N/A"
                  }
                ],
                "remarks": "Implemented by Network Control Plane"
              },
              {
                "uuid": "cae0c0e4-e3af-48ef-bb1a-8b8ab077a0fd",
                "control-id": "AC-4",
                "description": "Establishes a cryptographically secured overlay fabric with US-only geography enforcement.",
                "props": [
                  {
                    "name": "ksi-category",
                    "value": "KSI-UNKNOWN"
                  },
                  {
                    "name": "cisa-maturity",
                    "value": "Optimal"
                  },
                  {
                    "name": "evidence-source",
                    "value": "N/A"
                  }
                ],
                "remarks": "Implemented by Network Control Plane"
              }
            ]
          },
          {
            "uuid": "b969f290-f0b3-4cd8-b24d-3bb6a89c9c6c",
            "source": "https://github.com/GSA/fedramp-automation/raw/main/dist/content/rev5/baselines/json/FedRAMP_rev5_MODERATE-baseline_profile.json",
            "description": "Control implementations for Network Control Plane",
            "implemented-requirements": [
              {
                "uuid": "95634781-3255-408e-8efe-66f65b7d2623",
                "control-id": "CA-7",
                "description": "Real-time drift detection and automated remediation loop via ServiceNow and GitHub SCuBA.",
                "props": [
                  {
                    "name": "ksi-category",
                    "value": "KSI-UNKNOWN"
                  },
                  {
                    "name": "cisa-maturity",
                    "value": "Optimal"
                  },
                  {
                    "name": "evidence-source",
                    "value": "N/A"
                  }
                ],
                "remarks": "Implemented by Network Control Plane"
              },
              {
                "uuid": "846e7a43-9b1f-4a78-ad4d-3d2754455b51",
                "control-id": "CM-6",
                "description": "Real-time drift detection and automated remediation loop via ServiceNow and GitHub SCuBA.",
                "props": [
                  {
                    "name": "ksi-category",
                    "value": "KSI-UNKNOWN"
                  },
                  {
                    "name": "cisa-maturity",
                    "value": "Optimal"
                  },
                  {
                    "name": "evidence-source",
                    "value": "N/A"
                  }
                ],
                "remarks": "Implemented by Network Control Plane"
              },
              {
                "uuid": "582d3452-ff74-47bb-9061-6798476740a0",
                "control-id": "IR-4",
                "description": "Real-time drift detection and automated remediation loop via ServiceNow and GitHub SCuBA.",
                "props": [
                  {
                    "name": "ksi-category",
                    "value": "KSI-UNKNOWN"
                  },
                  {
                    "name": "cisa-maturity",
                    "value": "Optimal"
                  },
                  {
                    "name": "evidence-source",
                    "value": "N/A"
                  }
                ],
                "remarks": "Implemented by Network Control Plane"
              }
            ]
          },
          {
            "uuid": "af9510c0-8cbe-437c-ac6d-30fd5298b877",
            "source": "https://github.com/GSA/fedramp-automation/raw/main/dist/content/rev5/baselines/json/FedRAMP_rev5_MODERATE-baseline_profile.json",
            "description": "Control implementations for Network Control Plane",
            "implemented-requirements": [
              {
                "uuid": "aee97a3a-a2ba-40c3-93f8-9c189ba108ee",
                "control-id": "AC-4",
                "description": "Collapses legacy TIC 2.2 silos into a software-defined, identity-centric perimeter.",
                "props": [
                  {
                    "name": "ksi-category",
                    "value": "KSI-UNKNOWN"
                  },
                  {
                    "name": "cisa-maturity",
                    "value": "Advanced"
                  },
                  {
                    "name": "evidence-source",
                    "value": "N/A"
                  }
                ],
                "remarks": "Implemented by Network Control Plane"
              },
              {
                "uuid": "3ffe6ce1-197b-4b03-b487-082eb913aae4",
                "control-id": "SC-38",
                "description": "Collapses legacy TIC 2.2 silos into a software-defined, identity-centric perimeter.",
                "props": [
                  {
                    "name": "ksi-category",
                    "value": "KSI-UNKNOWN"
                  },
                  {
                    "name": "cisa-maturity",
                    "value": "Advanced"
                  },
                  {
                    "name": "evidence-source",
                    "value": "N/A"
                  }
                ],
                "remarks": "Implemented by Network Control Plane"
              }
            ]
          },
          {
            "uuid": "73ae5871-7c9a-44bb-9cc7-a6e2056033f8",
            "source": "https://github.com/GSA/fedramp-automation/raw/main/dist/content/rev5/baselines/json/FedRAMP_rev5_MODERATE-baseline_profile.json",
            "description": "Control implementations for Network Control Plane",
            "implemented-requirements": [
              {
                "uuid": "7eed7a00-6892-49b4-b3bf-d55add419c8a",
                "control-id": "SC-8",
                "description": "Anchors device and user trust to the GSA Federal Root CA with end-to-end channel binding.",
                "props": [
                  {
                    "name": "ksi-category",
                    "value": "KSI-UNKNOWN"
                  },
                  {
                    "name": "cisa-maturity",
                    "value": "Optimal"
                  },
                  {
                    "name": "evidence-source",
                    "value": "N/A"
                  }
                ],
                "remarks": "Implemented by Network Control Plane"
              },
              {
                "uuid": "d4aa1c5e-f7e1-4ae5-84bb-3781cd414de1",
                "control-id": "IA-3",
                "description": "Anchors device and user trust to the GSA Federal Root CA with end-to-end channel binding.",
                "props": [
                  {
                    "name": "ksi-category",
                    "value": "KSI-UNKNOWN"
                  },
                  {
                    "name": "cisa-maturity",
                    "value": "Optimal"
                  },
                  {
                    "name": "evidence-source",
                    "value": "N/A"
                  }
                ],
                "remarks": "Implemented by Network Control Plane"
              }
            ]
          }
        ]
      },
      {
        "uuid": "b8a35264-54bd-4ea8-a72d-0cd1047b37b3",
        "type": "service",
        "title": "Telemetry Control Plane",
        "description": "The substrate of truth for detection, diagnosis, governance, and automation",
        "props": [
          {
            "name": "uiao-pillar",
            "value": "TELEMETRY"
          },
          {
            "name": "subtitle",
            "value": "Detection, diagnosis, governance, and automation"
          },
          {
            "name": "component-id",
            "value": "component-telemetry"
          }
        ],
        "remarks": "[{\"name\": \"SIEM Platform\", \"role\": \"Aggregation, correlation, compliance\", \"capabilities\": []}, {\"name\": \"Cloud Monitoring Platform\", \"role\": \"Cloud-native telemetry\", \"capabilities\": []}, {\"name\": \"Network Performance Monitor\", \"role\": \"Network path truth\", \"capabilities\": []}, {\"name\": \"IPAM Platform\", \"role\": \"DNS/DHCP/IPAM evidence\", \"capabilities\": []}, {\"name\": \"Endpoint Detection Platform\", \"role\": \"Endpoint truth\", \"capabilities\": []}]",
        "control-implementations": [
          {
            "uuid": "af7b75b7-5045-49c6-bf70-9a1e6bf1328b",
            "source": "https://github.com/GSA/fedramp-automation/raw/main/dist/content/rev5/baselines/json/FedRAMP_rev5_MODERATE-baseline_profile.json",
            "description": "Control implementations for Telemetry Control Plane",
            "implemented-requirements": [
              {
                "uuid": "bf5bbcb1-89a2-4a52-b8bd-4f837b41b3a5",
                "control-id": "IA-2",
                "description": "Enforces phishing-resistant MFA and deterministic Identity-to-IP binding for all US-based endpoints via Entra ID and Infoblox.",
                "props": [
                  {
                    "name": "ksi-category",
                    "value": "KSI-UNKNOWN"
                  },
                  {
                    "name": "cisa-maturity",
                    "value": "Advanced"
                  },
                  {
                    "name": "evidence-source",
                    "value": "N/A"
                  }
                ],
                "remarks": "Implemented by Telemetry Control Plane"
              },
              {
                "uuid": "d61be5d4-efe1-466f-b250-06f42f252d42",
                "control-id": "IA-5",
                "description": "Enforces phishing-resistant MFA and deterministic Identity-to-IP binding for all US-based endpoints via Entra ID and Infoblox.",
                "props": [
                  {
                    "name": "ksi-category",
                    "value": "KSI-UNKNOWN"
                  },
                  {
                    "name": "cisa-maturity",
                    "value": "Advanced"
                  },
                  {
                    "name": "evidence-source",
                    "value": "N/A"
                  }
                ],
                "remarks": "Implemented by Telemetry Control Plane"
              },
              {
                "uuid": "7574d307-5fd7-428e-a801-0981868f5201",
                "control-id": "AC-19",
                "description": "Enforces phishing-resistant MFA and deterministic Identity-to-IP binding for all US-based endpoints via Entra ID and Infoblox.",
                "props": [
                  {
                    "name": "ksi-category",
                    "value": "KSI-UNKNOWN"
                  },
                  {
                    "name": "cisa-maturity",
                    "value": "Advanced"
                  },
                  {
                    "name": "evidence-source",
                    "value": "N/A"
                  }
                ],
                "remarks": "Implemented by Telemetry Control Plane"
              }
            ]
          },
          {
            "uuid": "1878c5f8-e4ac-4d82-9395-730715d58395",
            "source": "https://github.com/GSA/fedramp-automation/raw/main/dist/content/rev5/baselines/json/FedRAMP_rev5_MODERATE-baseline_profile.json",
            "description": "Control implementations for Telemetry Control Plane",
            "implemented-requirements": [
              {
                "uuid": "f84c6052-750d-4778-8836-4aa2b5cb406c",
                "control-id": "SC-7",
                "description": "Establishes a cryptographically secured overlay fabric with US-only geography enforcement.",
                "props": [
                  {
                    "name": "ksi-category",
                    "value": "KSI-UNKNOWN"
                  },
                  {
                    "name": "cisa-maturity",
                    "value": "Optimal"
                  },
                  {
                    "name": "evidence-source",
                    "value": "N/A"
                  }
                ],
                "remarks": "Implemented by Telemetry Control Plane"
              },
              {
                "uuid": "5caac6fc-4d57-4371-a871-073f6bc4c0a8",
                "control-id": "SC-8",
                "description": "Establishes a cryptographically secured overlay fabric with US-only geography enforcement.",
                "props": [
                  {
                    "name": "ksi-category",
                    "value": "KSI-UNKNOWN"
                  },
                  {
                    "name": "cisa-maturity",
                    "value": "Optimal"
                  },
                  {
                    "name": "evidence-source",
                    "value": "N/A"
                  }
                ],
                "remarks": "Implemented by Telemetry Control Plane"
              },
              {
                "uuid": "d16bd2c0-1099-41d4-9cd3-c32914d0624c",
                "control-id": "AC-4",
                "description": "Establishes a cryptographically secured overlay fabric with US-only geography enforcement.",
                "props": [
                  {
                    "name": "ksi-category",
                    "value": "KSI-UNKNOWN"
                  },
                  {
                    "name": "cisa-maturity",
                    "value": "Optimal"
                  },
                  {
                    "name": "evidence-source",
                    "value": "N/A"
                  }
                ],
                "remarks": "Implemented by Telemetry Control Plane"
              }
            ]
          },
          {
            "uuid": "62244afb-d564-4d87-93ce-c390e4f95638",
            "source": "https://github.com/GSA/fedramp-automation/raw/main/dist/content/rev5/baselines/json/FedRAMP_rev5_MODERATE-baseline_profile.json",
            "description": "Control implementations for Telemetry Control Plane",
            "implemented-requirements": [
              {
                "uuid": "72256ea6-4b0c-46e9-ba4e-97ed0ba1636a",
                "control-id": "CA-7",
                "description": "Real-time drift detection and automated remediation loop via ServiceNow and GitHub SCuBA.",
                "props": [
                  {
                    "name": "ksi-category",
                    "value": "KSI-UNKNOWN"
                  },
                  {
                    "name": "cisa-maturity",
                    "value": "Optimal"
                  },
                  {
                    "name": "evidence-source",
                    "value": "N/A"
                  }
                ],
                "remarks": "Implemented by Telemetry Control Plane"
              },
              {
                "uuid": "da27ca7d-1006-4186-9317-62ddef8d1d92",
                "control-id": "CM-6",
                "description": "Real-time drift detection and automated remediation loop via ServiceNow and GitHub SCuBA.",
                "props": [
                  {
                    "name": "ksi-category",
                    "value": "KSI-UNKNOWN"
                  },
                  {
                    "name": "cisa-maturity",
                    "value": "Optimal"
                  },
                  {
                    "name": "evidence-source",
                    "value": "N/A"
                  }
                ],
                "remarks": "Implemented by Telemetry Control Plane"
              },
              {
                "uuid": "d2c1902e-b664-4a9d-94a0-df5559c6c15b",
                "control-id": "IR-4",
                "description": "Real-time drift detection and automated remediation loop via ServiceNow and GitHub SCuBA.",
                "props": [
                  {
                    "name": "ksi-category",
                    "value": "KSI-UNKNOWN"
                  },
                  {
                    "name": "cisa-maturity",
                    "value": "Optimal"
                  },
                  {
                    "name": "evidence-source",
                    "value": "N/A"
                  }
                ],
                "remarks": "Implemented by Telemetry Control Plane"
              }
            ]
          },
          {
            "uuid": "db6639d4-b7da-4262-8e23-4d72620ea3f3",
            "source": "https://github.com/GSA/fedramp-automation/raw/main/dist/content/rev5/baselines/json/FedRAMP_rev5_MODERATE-baseline_profile.json",
            "description": "Control implementations for Telemetry Control Plane",
            "implemented-requirements": [
              {
                "uuid": "9e95ad25-beb9-4923-9dca-6dec54606fba",
                "control-id": "AC-4",
                "description": "Collapses legacy TIC 2.2 silos into a software-defined, identity-centric perimeter.",
                "props": [
                  {
                    "name": "ksi-category",
                    "value": "KSI-UNKNOWN"
                  },
                  {
                    "name": "cisa-maturity",
                    "value": "Advanced"
                  },
                  {
                    "name": "evidence-source",
                    "value": "N/A"
                  }
                ],
                "remarks": "Implemented by Telemetry Control Plane"
              },
              {
                "uuid": "a9ad2a06-fd19-4665-a02f-c660cdaa027f",
                "control-id": "SC-38",
                "description": "Collapses legacy TIC 2.2 silos into a software-defined, identity-centric perimeter.",
                "props": [
                  {
                    "name": "ksi-category",
                    "value": "KSI-UNKNOWN"
                  },
                  {
                    "name": "cisa-maturity",
                    "value": "Advanced"
                  },
                  {
                    "name": "evidence-source",
                    "value": "N/A"
                  }
                ],
                "remarks": "Implemented by Telemetry Control Plane"
              }
            ]
          },
          {
            "uuid": "f93b3c1f-59e6-45d1-b09d-3e441030a310",
            "source": "https://github.com/GSA/fedramp-automation/raw/main/dist/content/rev5/baselines/json/FedRAMP_rev5_MODERATE-baseline_profile.json",
            "description": "Control implementations for Telemetry Control Plane",
            "implemented-requirements": [
              {
                "uuid": "f15d8acc-944e-48c9-8706-58d4ec971171",
                "control-id": "SC-8",
                "description": "Anchors device and user trust to the GSA Federal Root CA with end-to-end channel binding.",
                "props": [
                  {
                    "name": "ksi-category",
                    "value": "KSI-UNKNOWN"
                  },
                  {
                    "name": "cisa-maturity",
                    "value": "Optimal"
                  },
                  {
                    "name": "evidence-source",
                    "value": "N/A"
                  }
                ],
                "remarks": "Implemented by Telemetry Control Plane"
              },
              {
                "uuid": "efe812f7-0877-4568-970d-c2bdd1931242",
                "control-id": "IA-3",
                "description": "Anchors device and user trust to the GSA Federal Root CA with end-to-end channel binding.",
                "props": [
                  {
                    "name": "ksi-category",
                    "value": "KSI-UNKNOWN"
                  },
                  {
                    "name": "cisa-maturity",
                    "value": "Optimal"
                  },
                  {
                    "name": "evidence-source",
                    "value": "N/A"
                  }
                ],
                "remarks": "Implemented by Telemetry Control Plane"
              }
            ]
          }
        ]
      },
      {
        "uuid": "e7cc1591-4b73-4463-97a6-29f888fd6057",
        "type": "service",
        "title": "Endpoint Control Plane",
        "description": "The identity-anchored, telemetry-driven governance layer for all devices",
        "props": [
          {
            "name": "uiao-pillar",
            "value": "ENDPOINT"
          },
          {
            "name": "subtitle",
            "value": "Identity-anchored, telemetry-driven device governance"
          },
          {
            "name": "component-id",
            "value": "component-endpoint"
          }
        ],
        "remarks": "[{\"name\": \"Endpoint Detection Platform\", \"role\": \"Endpoint detection and response\", \"capabilities\": []}, {\"name\": \"Endpoint Management Platform\", \"role\": \"Configuration and compliance management\", \"capabilities\": []}, {\"name\": \"Identity Provider Device Objects\", \"role\": \"Device identity anchoring\", \"capabilities\": []}]",
        "control-implementations": [
          {
            "uuid": "0fc1a41f-41ce-49b1-9b67-483e76c1eebf",
            "source": "https://github.com/GSA/fedramp-automation/raw/main/dist/content/rev5/baselines/json/FedRAMP_rev5_MODERATE-baseline_profile.json",
            "description": "Control implementations for Endpoint Control Plane",
            "implemented-requirements": [
              {
                "uuid": "48743af1-3fc4-4cde-9abb-5b7aaabd8b36",
                "control-id": "IA-2",
                "description": "Enforces phishing-resistant MFA and deterministic Identity-to-IP binding for all US-based endpoints via Entra ID and Infoblox.",
                "props": [
                  {
                    "name": "ksi-category",
                    "value": "KSI-UNKNOWN"
                  },
                  {
                    "name": "cisa-maturity",
                    "value": "Advanced"
                  },
                  {
                    "name": "evidence-source",
                    "value": "N/A"
                  }
                ],
                "remarks": "Implemented by Endpoint Control Plane"
              },
              {
                "uuid": "40da75d8-1582-4968-bd7c-3a1a1c64d635",
                "control-id": "IA-5",
                "description": "Enforces phishing-resistant MFA and deterministic Identity-to-IP binding for all US-based endpoints via Entra ID and Infoblox.",
                "props": [
                  {
                    "name": "ksi-category",
                    "value": "KSI-UNKNOWN"
                  },
                  {
                    "name": "cisa-maturity",
                    "value": "Advanced"
                  },
                  {
                    "name": "evidence-source",
                    "value": "N/A"
                  }
                ],
                "remarks": "Implemented by Endpoint Control Plane"
              },
              {
                "uuid": "c827c1bd-86d7-4298-a33c-50598e8633a7",
                "control-id": "AC-19",
                "description": "Enforces phishing-resistant MFA and deterministic Identity-to-IP binding for all US-based endpoints via Entra ID and Infoblox.",
                "props": [
                  {
                    "name": "ksi-category",
                    "value": "KSI-UNKNOWN"
                  },
                  {
                    "name": "cisa-maturity",
                    "value": "Advanced"
                  },
                  {
                    "name": "evidence-source",
                    "value": "N/A"
                  }
                ],
                "remarks": "Implemented by Endpoint Control Plane"
              }
            ]
          },
          {
            "uuid": "d0db1a6e-713b-495b-b627-e0c072e21565",
            "source": "https://github.com/GSA/fedramp-automation/raw/main/dist/content/rev5/baselines/json/FedRAMP_rev5_MODERATE-baseline_profile.json",
            "description": "Control implementations for Endpoint Control Plane",
            "implemented-requirements": [
              {
                "uuid": "f61fccc5-1a7f-432e-8295-9e8392c486c9",
                "control-id": "SC-7",
                "description": "Establishes a cryptographically secured overlay fabric with US-only geography enforcement.",
                "props": [
                  {
                    "name": "ksi-category",
                    "value": "KSI-UNKNOWN"
                  },
                  {
                    "name": "cisa-maturity",
                    "value": "Optimal"
                  },
                  {
                    "name": "evidence-source",
                    "value": "N/A"
                  }
                ],
                "remarks": "Implemented by Endpoint Control Plane"
              },
              {
                "uuid": "dc049293-d3d3-47ea-a36a-a0e03cfc8ecd",
                "control-id": "SC-8",
                "description": "Establishes a cryptographically secured overlay fabric with US-only geography enforcement.",
                "props": [
                  {
                    "name": "ksi-category",
                    "value": "KSI-UNKNOWN"
                  },
                  {
                    "name": "cisa-maturity",
                    "value": "Optimal"
                  },
                  {
                    "name": "evidence-source",
                    "value": "N/A"
                  }
                ],
                "remarks": "Implemented by Endpoint Control Plane"
              },
              {
                "uuid": "2ecd98ec-f74c-41ec-8bfe-cc7aa3cda1ed",
                "control-id": "AC-4",
                "description": "Establishes a cryptographically secured overlay fabric with US-only geography enforcement.",
                "props": [
                  {
                    "name": "ksi-category",
                    "value": "KSI-UNKNOWN"
                  },
                  {
                    "name": "cisa-maturity",
                    "value": "Optimal"
                  },
                  {
                    "name": "evidence-source",
                    "value": "N/A"
                  }
                ],
                "remarks": "Implemented by Endpoint Control Plane"
              }
            ]
          },
          {
            "uuid": "e893f255-afd0-4c28-85c2-638272f5648c",
            "source": "https://github.com/GSA/fedramp-automation/raw/main/dist/content/rev5/baselines/json/FedRAMP_rev5_MODERATE-baseline_profile.json",
            "description": "Control implementations for Endpoint Control Plane",
            "implemented-requirements": [
              {
                "uuid": "77266c5b-5626-4435-8eed-946f3e976c72",
                "control-id": "CA-7",
                "description": "Real-time drift detection and automated remediation loop via ServiceNow and GitHub SCuBA.",
                "props": [
                  {
                    "name": "ksi-category",
                    "value": "KSI-UNKNOWN"
                  },
                  {
                    "name": "cisa-maturity",
                    "value": "Optimal"
                  },
                  {
                    "name": "evidence-source",
                    "value": "N/A"
                  }
                ],
                "remarks": "Implemented by Endpoint Control Plane"
              },
              {
                "uuid": "af25bc17-6b5c-4f1d-b0d4-d1bfc3d3db74",
                "control-id": "CM-6",
                "description": "Real-time drift detection and automated remediation loop via ServiceNow and GitHub SCuBA.",
                "props": [
                  {
                    "name": "ksi-category",
                    "value": "KSI-UNKNOWN"
                  },
                  {
                    "name": "cisa-maturity",
                    "value": "Optimal"
                  },
                  {
                    "name": "evidence-source",
                    "value": "N/A"
                  }
                ],
                "remarks": "Implemented by Endpoint Control Plane"
              },
              {
                "uuid": "18f69a50-9a4d-451b-ae85-ed7dc2e9f59f",
                "control-id": "IR-4",
                "description": "Real-time drift detection and automated remediation loop via ServiceNow and GitHub SCuBA.",
                "props": [
                  {
                    "name": "ksi-category",
                    "value": "KSI-UNKNOWN"
                  },
                  {
                    "name": "cisa-maturity",
                    "value": "Optimal"
                  },
                  {
                    "name": "evidence-source",
                    "value": "N/A"
                  }
                ],
                "remarks": "Implemented by Endpoint Control Plane"
              }
            ]
          },
          {
            "uuid": "e356352e-9b5e-45ef-b5aa-155548f34587",
            "source": "https://github.com/GSA/fedramp-automation/raw/main/dist/content/rev5/baselines/json/FedRAMP_rev5_MODERATE-baseline_profile.json",
            "description": "Control implementations for Endpoint Control Plane",
            "implemented-requirements": [
              {
                "uuid": "6a7ba71a-27a3-4d31-85dd-4d9a117be59c",
                "control-id": "AC-4",
                "description": "Collapses legacy TIC 2.2 silos into a software-defined, identity-centric perimeter.",
                "props": [
                  {
                    "name": "ksi-category",
                    "value": "KSI-UNKNOWN"
                  },
                  {
                    "name": "cisa-maturity",
                    "value": "Advanced"
                  },
                  {
                    "name": "evidence-source",
                    "value": "N/A"
                  }
                ],
                "remarks": "Implemented by Endpoint Control Plane"
              },
              {
                "uuid": "e8276cf3-db90-45e6-ae16-01c19e6280c6",
                "control-id": "SC-38",
                "description": "Collapses legacy TIC 2.2 silos into a software-defined, identity-centric perimeter.",
                "props": [
                  {
                    "name": "ksi-category",
                    "value": "KSI-UNKNOWN"
                  },
                  {
                    "name": "cisa-maturity",
                    "value": "Advanced"
                  },
                  {
                    "name": "evidence-source",
                    "value": "N/A"
                  }
                ],
                "remarks": "Implemented by Endpoint Control Plane"
              }
            ]
          },
          {
            "uuid": "25d1b802-691c-4abf-a814-7ed60f5e1e53",
            "source": "https://github.com/GSA/fedramp-automation/raw/main/dist/content/rev5/baselines/json/FedRAMP_rev5_MODERATE-baseline_profile.json",
            "description": "Control implementations for Endpoint Control Plane",
            "implemented-requirements": [
              {
                "uuid": "9b7ea3bc-c57d-4169-875e-fd8e13e1401b",
                "control-id": "SC-8",
                "description": "Anchors device and user trust to the GSA Federal Root CA with end-to-end channel binding.",
                "props": [
                  {
                    "name": "ksi-category",
                    "value": "KSI-UNKNOWN"
                  },
                  {
                    "name": "cisa-maturity",
                    "value": "Optimal"
                  },
                  {
                    "name": "evidence-source",
                    "value": "N/A"
                  }
                ],
                "remarks": "Implemented by Endpoint Control Plane"
              },
              {
                "uuid": "a02111e0-381a-413f-870e-e3f2ca5d1c9c",
                "control-id": "IA-3",
                "description": "Anchors device and user trust to the GSA Federal Root CA with end-to-end channel binding.",
                "props": [
                  {
                    "name": "ksi-category",
                    "value": "KSI-UNKNOWN"
                  },
                  {
                    "name": "cisa-maturity",
                    "value": "Optimal"
                  },
                  {
                    "name": "evidence-source",
                    "value": "N/A"
                  }
                ],
                "remarks": "Implemented by Endpoint Control Plane"
              }
            ]
          }
        ]
      },
      {
        "uuid": "bc852860-8545-4eb2-9226-57dee58b0fbd",
        "type": "service",
        "title": "Security Control Plane",
        "description": "The enforcement, validation, and assurance substrate for Zero Trust across all systems, identities, networks, and workloads",
        "props": [
          {
            "name": "uiao-pillar",
            "value": "SECURITY"
          },
          {
            "name": "subtitle",
            "value": "Zero Trust enforcement, validation, and assurance"
          },
          {
            "name": "component-id",
            "value": "component-security"
          }
        ],
        "remarks": "[]",
        "control-implementations": [
          {
            "uuid": "7dc291bd-4d78-43c7-8817-e173457af3c6",
            "source": "https://github.com/GSA/fedramp-automation/raw/main/dist/content/rev5/baselines/json/FedRAMP_rev5_MODERATE-baseline_profile.json",
            "description": "Control implementations for Security Control Plane",
            "implemented-requirements": [
              {
                "uuid": "4183db86-d465-455e-b317-a46a24c30cbf",
                "control-id": "IA-2",
                "description": "Enforces phishing-resistant MFA and deterministic Identity-to-IP binding for all US-based endpoints via Entra ID and Infoblox.",
                "props": [
                  {
                    "name": "ksi-category",
                    "value": "KSI-UNKNOWN"
                  },
                  {
                    "name": "cisa-maturity",
                    "value": "Advanced"
                  },
                  {
                    "name": "evidence-source",
                    "value": "N/A"
                  }
                ],
                "remarks": "Implemented by Security Control Plane"
              },
              {
                "uuid": "1a5337c1-b9b3-4d2a-be0f-cb9e496e3889",
                "control-id": "IA-5",
                "description": "Enforces phishing-resistant MFA and deterministic Identity-to-IP binding for all US-based endpoints via Entra ID and Infoblox.",
                "props": [
                  {
                    "name": "ksi-category",
                    "value": "KSI-UNKNOWN"
                  },
                  {
                    "name": "cisa-maturity",
                    "value": "Advanced"
                  },
                  {
                    "name": "evidence-source",
                    "value": "N/A"
                  }
                ],
                "remarks": "Implemented by Security Control Plane"
              },
              {
                "uuid": "7371a535-b93d-4257-b534-45b36390e846",
                "control-id": "AC-19",
                "description": "Enforces phishing-resistant MFA and deterministic Identity-to-IP binding for all US-based endpoints via Entra ID and Infoblox.",
                "props": [
                  {
                    "name": "ksi-category",
                    "value": "KSI-UNKNOWN"
                  },
                  {
                    "name": "cisa-maturity",
                    "value": "Advanced"
                  },
                  {
                    "name": "evidence-source",
                    "value": "N/A"
                  }
                ],
                "remarks": "Implemented by Security Control Plane"
              }
            ]
          },
          {
            "uuid": "6a3de5f6-b2de-49cc-9021-3320442e9e36",
            "source": "https://github.com/GSA/fedramp-automation/raw/main/dist/content/rev5/baselines/json/FedRAMP_rev5_MODERATE-baseline_profile.json",
            "description": "Control implementations for Security Control Plane",
            "implemented-requirements": [
              {
                "uuid": "22b90fc3-4580-4aa0-985b-6b5932fb9db6",
                "control-id": "SC-7",
                "description": "Establishes a cryptographically secured overlay fabric with US-only geography enforcement.",
                "props": [
                  {
                    "name": "ksi-category",
                    "value": "KSI-UNKNOWN"
                  },
                  {
                    "name": "cisa-maturity",
                    "value": "Optimal"
                  },
                  {
                    "name": "evidence-source",
                    "value": "N/A"
                  }
                ],
                "remarks": "Implemented by Security Control Plane"
              },
              {
                "uuid": "6af44f26-ae16-48ab-9d86-061baae5db66",
                "control-id": "SC-8",
                "description": "Establishes a cryptographically secured overlay fabric with US-only geography enforcement.",
                "props": [
                  {
                    "name": "ksi-category",
                    "value": "KSI-UNKNOWN"
                  },
                  {
                    "name": "cisa-maturity",
                    "value": "Optimal"
                  },
                  {
                    "name": "evidence-source",
                    "value": "N/A"
                  }
                ],
                "remarks": "Implemented by Security Control Plane"
              },
              {
                "uuid": "7ec76c2f-5fe2-4a75-8cc2-c2e79856223a",
                "control-id": "AC-4",
                "description": "Establishes a cryptographically secured overlay fabric with US-only geography enforcement.",
                "props": [
                  {
                    "name": "ksi-category",
                    "value": "KSI-UNKNOWN"
                  },
                  {
                    "name": "cisa-maturity",
                    "value": "Optimal"
                  },
                  {
                    "name": "evidence-source",
                    "value": "N/A"
                  }
                ],
                "remarks": "Implemented by Security Control Plane"
              }
            ]
          },
          {
            "uuid": "5a3be544-ce9d-43c4-a65d-5e717094446a",
            "source": "https://github.com/GSA/fedramp-automation/raw/main/dist/content/rev5/baselines/json/FedRAMP_rev5_MODERATE-baseline_profile.json",
            "description": "Control implementations for Security Control Plane",
            "implemented-requirements": [
              {
                "uuid": "1c7121cb-3d1d-41db-a074-3989b3543e55",
                "control-id": "CA-7",
                "description": "Real-time drift detection and automated remediation loop via ServiceNow and GitHub SCuBA.",
                "props": [
                  {
                    "name": "ksi-category",
                    "value": "KSI-UNKNOWN"
                  },
                  {
                    "name": "cisa-maturity",
                    "value": "Optimal"
                  },
                  {
                    "name": "evidence-source",
                    "value": "N/A"
                  }
                ],
                "remarks": "Implemented by Security Control Plane"
              },
              {
                "uuid": "61455512-2392-4c6e-981f-a129322164e6",
                "control-id": "CM-6",
                "description": "Real-time drift detection and automated remediation loop via ServiceNow and GitHub SCuBA.",
                "props": [
                  {
                    "name": "ksi-category",
                    "value": "KSI-UNKNOWN"
                  },
                  {
                    "name": "cisa-maturity",
                    "value": "Optimal"
                  },
                  {
                    "name": "evidence-source",
                    "value": "N/A"
                  }
                ],
                "remarks": "Implemented by Security Control Plane"
              },
              {
                "uuid": "3708dc11-b2c4-43d8-8e7a-29e991633bd0",
                "control-id": "IR-4",
                "description": "Real-time drift detection and automated remediation loop via ServiceNow and GitHub SCuBA.",
                "props": [
                  {
                    "name": "ksi-category",
                    "value": "KSI-UNKNOWN"
                  },
                  {
                    "name": "cisa-maturity",
                    "value": "Optimal"
                  },
                  {
                    "name": "evidence-source",
                    "value": "N/A"
                  }
                ],
                "remarks": "Implemented by Security Control Plane"
              }
            ]
          },
          {
            "uuid": "74017453-5277-4757-899b-21e8c5e160fb",
            "source": "https://github.com/GSA/fedramp-automation/raw/main/dist/content/rev5/baselines/json/FedRAMP_rev5_MODERATE-baseline_profile.json",
            "description": "Control implementations for Security Control Plane",
            "implemented-requirements": [
              {
                "uuid": "199cdbe8-aef0-4c33-8d32-1291bc499038",
                "control-id": "AC-4",
                "description": "Collapses legacy TIC 2.2 silos into a software-defined, identity-centric perimeter.",
                "props": [
                  {
                    "name": "ksi-category",
                    "value": "KSI-UNKNOWN"
                  },
                  {
                    "name": "cisa-maturity",
                    "value": "Advanced"
                  },
                  {
                    "name": "evidence-source",
                    "value": "N/A"
                  }
                ],
                "remarks": "Implemented by Security Control Plane"
              },
              {
                "uuid": "55b73576-f313-4d83-963c-8ba2e3f5c090",
                "control-id": "SC-38",
                "description": "Collapses legacy TIC 2.2 silos into a software-defined, identity-centric perimeter.",
                "props": [
                  {
                    "name": "ksi-category",
                    "value": "KSI-UNKNOWN"
                  },
                  {
                    "name": "cisa-maturity",
                    "value": "Advanced"
                  },
                  {
                    "name": "evidence-source",
                    "value": "N/A"
                  }
                ],
                "remarks": "Implemented by Security Control Plane"
              }
            ]
          },
          {
            "uuid": "4f44f549-2152-4799-876b-33d5de3f0fd4",
            "source": "https://github.com/GSA/fedramp-automation/raw/main/dist/content/rev5/baselines/json/FedRAMP_rev5_MODERATE-baseline_profile.json",
            "description": "Control implementations for Security Control Plane",
            "implemented-requirements": [
              {
                "uuid": "f5c25bda-8da5-4ea7-82d3-90b1b4d55c9a",
                "control-id": "SC-8",
                "description": "Anchors device and user trust to the GSA Federal Root CA with end-to-end channel binding.",
                "props": [
                  {
                    "name": "ksi-category",
                    "value": "KSI-UNKNOWN"
                  },
                  {
                    "name": "cisa-maturity",
                    "value": "Optimal"
                  },
                  {
                    "name": "evidence-source",
                    "value": "N/A"
                  }
                ],
                "remarks": "Implemented by Security Control Plane"
              },
              {
                "uuid": "77962810-e596-4c73-9d2b-d2fea201b232",
                "control-id": "IA-3",
                "description": "Anchors device and user trust to the GSA Federal Root CA with end-to-end channel binding.",
                "props": [
                  {
                    "name": "ksi-category",
                    "value": "KSI-UNKNOWN"
                  },
                  {
                    "name": "cisa-maturity",
                    "value": "Optimal"
                  },
                  {
                    "name": "evidence-source",
                    "value": "N/A"
                  }
                ],
                "remarks": "Implemented by Security Control Plane"
              }
            ]
          }
        ]
      }
    ],
    "capabilities": []
  }
}